[
  {
    "text": "[SQUEAKING]",
    "start": "0",
    "end": "2455"
  },
  {
    "text": "[RUSTLING]",
    "start": "2455",
    "end": "4418"
  },
  {
    "text": "[CLICKING]",
    "start": "4419",
    "end": "14559"
  },
  {
    "text": "RICHARD DE NEUFVILLE: So\nthe first portions of it,",
    "start": "14560",
    "end": "19960"
  },
  {
    "text": "the title is the\n\"Drivers of Flexibility.\"",
    "start": "19960",
    "end": "23289"
  },
  {
    "text": "That is, through our\nexploration of the fact",
    "start": "23290",
    "end": "27130"
  },
  {
    "text": "that the forecast\nis always wrong,",
    "start": "27130",
    "end": "28900"
  },
  {
    "text": "that there's uncertainty,\nand the observation",
    "start": "28900",
    "end": "32770"
  },
  {
    "text": "that we need to explore\nwhat might happen,",
    "start": "32770",
    "end": "36850"
  },
  {
    "text": "there are certain factors\nthat make it much more likely",
    "start": "36850",
    "end": "40960"
  },
  {
    "text": "that we should have\nflexibility to not.",
    "start": "40960",
    "end": "45070"
  },
  {
    "text": "And on the other hand, there\nare things that act against it.",
    "start": "45070",
    "end": "48650"
  },
  {
    "text": "There are reasons why\nflexibility is either not",
    "start": "48650",
    "end": "51790"
  },
  {
    "text": "desirable or, the most important\nthing I want to emphasize,",
    "start": "51790",
    "end": "58270"
  },
  {
    "text": "why there are certain factors\nin the practice of engineering,",
    "start": "58270",
    "end": "62260"
  },
  {
    "text": "the paradigm of\nengineering as we have it",
    "start": "62260",
    "end": "64569"
  },
  {
    "text": "that act against the idea\nthat we should be flexible.",
    "start": "64569",
    "end": "67540"
  },
  {
    "text": "And this is what\nthis topic is about.",
    "start": "67540",
    "end": "69920"
  },
  {
    "text": "That is, what are\nthe issues that",
    "start": "69920",
    "end": "72400"
  },
  {
    "text": "are for and against\nflexibility and how",
    "start": "72400",
    "end": "74920"
  },
  {
    "text": "we might deal with them?",
    "start": "74920",
    "end": "76840"
  },
  {
    "text": "We can come back to some of\nthe implications later on.",
    "start": "76840",
    "end": "81079"
  },
  {
    "text": "But for the moment, I want\nto address these five issues.",
    "start": "81080",
    "end": "86510"
  },
  {
    "text": "So a key aspect\nof flexibility is",
    "start": "86510",
    "end": "90340"
  },
  {
    "text": "to delay the design and\nmanagement decisions.",
    "start": "90340",
    "end": "92740"
  },
  {
    "text": "That is say, all right, we're\nprepared to do something.",
    "start": "92740",
    "end": "96880"
  },
  {
    "text": "For example, in\nthe garage case, we",
    "start": "96880",
    "end": "99250"
  },
  {
    "text": "are ready to add extra floors\nif it seems appropriate.",
    "start": "99250",
    "end": "104450"
  },
  {
    "text": "But we're not going to act on it\nuntil we know what's happening.",
    "start": "104450",
    "end": "110049"
  },
  {
    "text": "We're not going to,\nquote, \"pull the trigger,\"",
    "start": "110050",
    "end": "112000"
  },
  {
    "text": "is a expression often\nused in practice on it",
    "start": "112000",
    "end": "116320"
  },
  {
    "text": "until we know that the\ncircumstances are definitely",
    "start": "116320",
    "end": "119680"
  },
  {
    "text": "right.",
    "start": "119680",
    "end": "120960"
  },
  {
    "text": "So there are, however, a\nway of thinking about it",
    "start": "120960",
    "end": "126810"
  },
  {
    "text": "of saying, well,\nwhy mess around?",
    "start": "126810",
    "end": "129209"
  },
  {
    "text": "We're going to need this.",
    "start": "129210",
    "end": "130590"
  },
  {
    "text": "Why don't we build it now?",
    "start": "130590",
    "end": "132239"
  },
  {
    "text": "Why shouldn't we just make\nup our minds, do it right,",
    "start": "132240",
    "end": "134850"
  },
  {
    "text": "rather than dithering around and\nnot knowing what we're doing?",
    "start": "134850",
    "end": "137820"
  },
  {
    "text": "Why don't we take action\nand be real leaders?",
    "start": "137820",
    "end": "141940"
  },
  {
    "text": "So this is the discussion\nI'd like to address.",
    "start": "141940",
    "end": "145950"
  },
  {
    "start": "145950",
    "end": "148680"
  },
  {
    "text": "So I got to call out\nfive factors, which",
    "start": "148680",
    "end": "152489"
  },
  {
    "text": "are driving for and against the\ndesirability of flexibility.",
    "start": "152490",
    "end": "158420"
  },
  {
    "text": "The basic one, of course,\nis their uncertainty.",
    "start": "158420",
    "end": "161420"
  },
  {
    "text": "If we didn't have\nuncertainty, if we absolutely",
    "start": "161420",
    "end": "164157"
  },
  {
    "text": "knew what was going\nto happen, then we",
    "start": "164157",
    "end": "165739"
  },
  {
    "text": "should optimize for that\none particular state.",
    "start": "165740",
    "end": "169430"
  },
  {
    "text": "But the fact is we don't\nknow what's going to happen.",
    "start": "169430",
    "end": "171890"
  },
  {
    "text": "Not only we don't\nknow what's going",
    "start": "171890",
    "end": "173720"
  },
  {
    "text": "to happen next year\nor the year after",
    "start": "173720",
    "end": "177090"
  },
  {
    "text": "or the year after\nthat and so on,",
    "start": "177090",
    "end": "179190"
  },
  {
    "text": "but we don't know\nin what sequence.",
    "start": "179190",
    "end": "180860"
  },
  {
    "text": "And next year may be good and\nnext year after that may be bad",
    "start": "180860",
    "end": "183590"
  },
  {
    "text": "or vice versa, and those\nhave different implications",
    "start": "183590",
    "end": "186560"
  },
  {
    "text": "for the profitability of the\nvalue of the system as a whole.",
    "start": "186560",
    "end": "191550"
  },
  {
    "text": "The second one is this notion\nof economies of scale, which I",
    "start": "191550",
    "end": "194510"
  },
  {
    "text": "want to go into in more detail.",
    "start": "194510",
    "end": "197670"
  },
  {
    "text": "But it basically says,\nif you build it larger,",
    "start": "197670",
    "end": "201080"
  },
  {
    "text": "it is cheaper per\nunit to build it.",
    "start": "201080",
    "end": "203660"
  },
  {
    "text": "And therefore, don't mess around\nwith small, uneconomical units",
    "start": "203660",
    "end": "209090"
  },
  {
    "text": "of capacity.",
    "start": "209090",
    "end": "210080"
  },
  {
    "text": "Go for the big thing,\nsave yourself money,",
    "start": "210080",
    "end": "212480"
  },
  {
    "text": "and don't delay.",
    "start": "212480",
    "end": "215959"
  },
  {
    "text": "The third one, which is\ndirectly opposite to that,",
    "start": "215960",
    "end": "219050"
  },
  {
    "text": "is the discount\nrate, which basically",
    "start": "219050",
    "end": "221330"
  },
  {
    "text": "says, if you delay decisions,\nif you build the capacity later",
    "start": "221330",
    "end": "226580"
  },
  {
    "text": "on, you'll be doing it at\na discounted rate in terms",
    "start": "226580",
    "end": "230660"
  },
  {
    "text": "of the present so that it's\ncheaper to build something",
    "start": "230660",
    "end": "235100"
  },
  {
    "text": "in the future than it is now\non a present value basis.",
    "start": "235100",
    "end": "239870"
  },
  {
    "text": "Adding to that effect is\nthis notion of learning,",
    "start": "239870",
    "end": "243379"
  },
  {
    "text": "that, if you are doing\nsomething reasonably new",
    "start": "243380",
    "end": "247220"
  },
  {
    "text": "that you haven't made\nmillions of already,",
    "start": "247220",
    "end": "249800"
  },
  {
    "text": "you're building a power plant,\nfor example, of a new design",
    "start": "249800",
    "end": "257180"
  },
  {
    "text": "and then you're going to build\nanother one or an oil platform",
    "start": "257180",
    "end": "260239"
  },
  {
    "text": "that, when you use the same\ndesign second time, third time,",
    "start": "260240",
    "end": "264960"
  },
  {
    "text": "fourth time, you've\nfigured out or the team,",
    "start": "264960",
    "end": "267800"
  },
  {
    "text": "the company has figured out\nways to organize things better,",
    "start": "267800",
    "end": "272509"
  },
  {
    "text": "maybe some design improvements,\nbut the cost per unit",
    "start": "272510",
    "end": "277330"
  },
  {
    "text": "typically decrease\noften significantly when",
    "start": "277330",
    "end": "281470"
  },
  {
    "text": "you repeat the same\ndesign, the same module.",
    "start": "281470",
    "end": "284270"
  },
  {
    "text": "So the practice\nof having modules,",
    "start": "284270",
    "end": "289240"
  },
  {
    "text": "there's an advantage to it.",
    "start": "289240",
    "end": "291650"
  },
  {
    "text": "And then finally, there's this\nnotion of competitive gaming,",
    "start": "291650",
    "end": "295009"
  },
  {
    "text": "which is quite\ncomplex, which I'm not",
    "start": "295010",
    "end": "297140"
  },
  {
    "text": "going to go into detail here\nbut to suggest what it is.",
    "start": "297140",
    "end": "302210"
  },
  {
    "text": "But the basic idea is that\nsometimes an organization",
    "start": "302210",
    "end": "306319"
  },
  {
    "text": "or a group or an\nindividual wants",
    "start": "306320",
    "end": "308780"
  },
  {
    "text": "to scare away its competitors\nby saying, I'm doing it",
    "start": "308780",
    "end": "313580"
  },
  {
    "text": "and I'm going to be the\nleader in this area.",
    "start": "313580",
    "end": "317159"
  },
  {
    "text": "And if you try to compete\nwith me, you'll lose.",
    "start": "317160",
    "end": "319310"
  },
  {
    "text": "So at some point, it is an\nacceptable and desirable",
    "start": "319310",
    "end": "323600"
  },
  {
    "text": "strategy to act first\nnow, be number one,",
    "start": "323600",
    "end": "327230"
  },
  {
    "text": "and get the benefits of that.",
    "start": "327230",
    "end": "330735"
  },
  {
    "text": "On the other hand,\nit also means you're",
    "start": "330735",
    "end": "332360"
  },
  {
    "text": "more likely to make\nthe mistakes but still",
    "start": "332360",
    "end": "334370"
  },
  {
    "text": "that notion of their\nstrategic reasons",
    "start": "334370",
    "end": "339320"
  },
  {
    "text": "to play in the game of\ncompetitive games to not delay.",
    "start": "339320",
    "end": "345330"
  },
  {
    "text": "So these are four\nelements I want to discuss",
    "start": "345330",
    "end": "348830"
  },
  {
    "text": "in the next little while.",
    "start": "348830",
    "end": "352849"
  },
  {
    "text": "So first of all, I want\nto revoke the notion",
    "start": "352850",
    "end": "357800"
  },
  {
    "text": "of uncertainty a bit.",
    "start": "357800",
    "end": "359310"
  },
  {
    "text": "So a lot of people will\nuse uncertainty and risk",
    "start": "359310",
    "end": "366350"
  },
  {
    "text": "as sort of equivalence, which\nimplies, since risk is saying,",
    "start": "366350",
    "end": "372020"
  },
  {
    "text": "oh, this is a bad\nthing, you don't",
    "start": "372020",
    "end": "375500"
  },
  {
    "text": "talk about the risk of\nwinning the lottery.",
    "start": "375500",
    "end": "378470"
  },
  {
    "text": "I mean, this is a good thing.",
    "start": "378470",
    "end": "379940"
  },
  {
    "text": "But you talk about risk\nin terms of bad things.",
    "start": "379940",
    "end": "383030"
  },
  {
    "text": "I risk failing my exam.",
    "start": "383030",
    "end": "385190"
  },
  {
    "text": "I risk losing my way.",
    "start": "385190",
    "end": "388970"
  },
  {
    "text": "I risk losing some\nmoney, whatever.",
    "start": "388970",
    "end": "393120"
  },
  {
    "text": "So I think that the notion of\nthinking of uncertainty as risk",
    "start": "393120",
    "end": "399680"
  },
  {
    "text": "is not a good mental state.",
    "start": "399680",
    "end": "403370"
  },
  {
    "text": "Because it leads to the\nidea, if risk is bad,",
    "start": "403370",
    "end": "407000"
  },
  {
    "text": "I'm going to try\nto stamp it out.",
    "start": "407000",
    "end": "409220"
  },
  {
    "text": "Stew Myers used to\nuse that expression.",
    "start": "409220",
    "end": "412217"
  },
  {
    "text": "I'm going to stamp it out.",
    "start": "412217",
    "end": "413300"
  },
  {
    "text": "It's not good.",
    "start": "413300",
    "end": "414229"
  },
  {
    "text": "We're going to eliminate it.",
    "start": "414230",
    "end": "415590"
  },
  {
    "text": "Well, first of all,\nyou can't eliminate.",
    "start": "415590",
    "end": "418100"
  },
  {
    "text": "But then secondly,\nthe uncertainty",
    "start": "418100",
    "end": "419990"
  },
  {
    "text": "can be good, that you are\ndeveloping a new product",
    "start": "419990",
    "end": "424280"
  },
  {
    "text": "and maybe it will\nbe a winner, that",
    "start": "424280",
    "end": "426770"
  },
  {
    "text": "the uncertainty of your gain,\nit can be exactly what you want.",
    "start": "426770",
    "end": "433310"
  },
  {
    "text": "If you're a startup,\nyou know from the data",
    "start": "433310",
    "end": "437780"
  },
  {
    "text": "that most startups fail.",
    "start": "437780",
    "end": "439730"
  },
  {
    "text": "If you're simply going on\nthe basis that startups fail,",
    "start": "439730",
    "end": "442850"
  },
  {
    "text": "you should never\nget involved in it.",
    "start": "442850",
    "end": "444350"
  },
  {
    "text": "If you're risk-averse,\nnever get involved in it.",
    "start": "444350",
    "end": "446990"
  },
  {
    "text": "But the attractiveness\nof startups",
    "start": "446990",
    "end": "449660"
  },
  {
    "text": "is that they may break through\nand that upside uncertainty",
    "start": "449660",
    "end": "453680"
  },
  {
    "text": "is what drives that\nkind of activity.",
    "start": "453680",
    "end": "459020"
  },
  {
    "text": "And I encourage you to talk\nabout uncertainties in general",
    "start": "459020",
    "end": "462860"
  },
  {
    "text": "rather than risk and\nrecognize that we're",
    "start": "462860",
    "end": "465740"
  },
  {
    "text": "talking about a range\nof future possibilities.",
    "start": "465740",
    "end": "470020"
  },
  {
    "start": "470020",
    "end": "476000"
  }
]