[
  {
    "start": "0",
    "end": "108000"
  },
  {
    "text": "so let me start with a with a story of how I started this journey I guess when",
    "start": "4860",
    "end": "11340"
  },
  {
    "text": "I was in college I was overworked and very anxious and I didn't figure out until senior",
    "start": "11340",
    "end": "19260"
  },
  {
    "text": "year that afternoons were a good time to get homework done so I procrastinated and then I stayed up all night doing homework as maybe you have to",
    "start": "19260",
    "end": "26660"
  },
  {
    "text": "and there was one night that I remember distinctly where I was so stressed out",
    "start": "26660",
    "end": "31980"
  },
  {
    "text": "and I don't even know what all I had to do and at two in the morning I I said",
    "start": "31980",
    "end": "37800"
  },
  {
    "text": "you know what I just need to go out and clear my clear my head and go for a short walk",
    "start": "37800",
    "end": "43739"
  },
  {
    "text": "um and I did and I went outside it was Pitch Black I went to a small school there wasn't a lot of light",
    "start": "43739",
    "end": "49320"
  },
  {
    "text": "um and as I was walking all of a sudden there was this gigantic truck coming out from this um from side street and about",
    "start": "49320",
    "end": "56579"
  },
  {
    "text": "to hit me and I jumped out of the way and I didn't get hurt and everything was okay and then I came back to my dorm room and",
    "start": "56579",
    "end": "63000"
  },
  {
    "text": "I'm like you know what I thought there couldn't have been a truck there that street was way way too small",
    "start": "63000",
    "end": "69659"
  },
  {
    "text": "like it just couldn't have worked and so that's when I really started realizing what I'm doing to myself is really not",
    "start": "69659",
    "end": "76860"
  },
  {
    "text": "very healthy and it's probably not setting me up for success and I need to give this some thought and so that's",
    "start": "76860",
    "end": "82680"
  },
  {
    "text": "when I started thinking more about this and and reading more about this topic and",
    "start": "82680",
    "end": "88080"
  },
  {
    "text": "um and you know these many years later I'm still on this journey as my family",
    "start": "88080",
    "end": "94080"
  },
  {
    "text": "will attest I'm I haven't gotten it all figured out but hopefully there are a few lessons I can share with you today",
    "start": "94080",
    "end": "100520"
  },
  {
    "text": "and hopefully that will start you on your own Journey or continue to motivate",
    "start": "100520",
    "end": "105900"
  },
  {
    "text": "you just a little bit more about myself",
    "start": "105900",
    "end": "111180"
  },
  {
    "start": "108000",
    "end": "164000"
  },
  {
    "text": "um I work at Google we have a booth outside please go check it out during the break I lead engineering team so",
    "start": "111180",
    "end": "117720"
  },
  {
    "text": "most of my day is spent thinking about disaster recovery and control planes and",
    "start": "117720",
    "end": "122820"
  },
  {
    "text": "failovers and and all kinds of things like that so I can talk about that for ages as well but I also lead engineering",
    "start": "122820",
    "end": "129539"
  },
  {
    "text": "teams I lead a team right now of about 100 people a little more depending on",
    "start": "129539",
    "end": "134760"
  },
  {
    "text": "how you count and so a lot of what I do every day is really also thinking about",
    "start": "134760",
    "end": "139860"
  },
  {
    "text": "how do these people work together how do these teams work together how can I make my my org a high functioning org that",
    "start": "139860",
    "end": "147180"
  },
  {
    "text": "works well and delivers a lot of impact and um honestly a lot of that has to do with",
    "start": "147180",
    "end": "154440"
  },
  {
    "text": "people and people are very complicated so what we're talking about here today actually feeds very nicely into this",
    "start": "154440",
    "end": "163099"
  },
  {
    "start": "164000",
    "end": "260000"
  },
  {
    "text": "so let's talk a little bit about positive psychology so I am not a",
    "start": "164940",
    "end": "170879"
  },
  {
    "text": "psychologist by training a lot of this is material that I've read on my own and listened to books and and podcasts and",
    "start": "170879",
    "end": "177660"
  },
  {
    "text": "things like that about um but you know there's a lot that we",
    "start": "177660",
    "end": "183360"
  },
  {
    "text": "can learn and I think uh you know all of us have been trained to absorb lots of material and one of the things that I",
    "start": "183360",
    "end": "190920"
  },
  {
    "text": "always tell people on my team who are aspiring to be managers some of them are is there's a lot to learn and a lot of",
    "start": "190920",
    "end": "198840"
  },
  {
    "text": "people have figured out a lot of things before us and you don't need to start from scratch",
    "start": "198840",
    "end": "204300"
  },
  {
    "text": "so what is positive psychology um so positive psychology is really the way",
    "start": "204300",
    "end": "212580"
  },
  {
    "text": "to think about it is the psychology of thriving like how do you put yourself and your family and your team and your",
    "start": "212580",
    "end": "219180"
  },
  {
    "text": "community in a place where they can Thrive um this is what it is not it is not just",
    "start": "219180",
    "end": "227640"
  },
  {
    "text": "giggly fun and you know happy hours and things like that and what people tend to uh you know what what Greek philosophers",
    "start": "227640",
    "end": "234720"
  },
  {
    "text": "will will call Hedonism where the idea is that pleasure is the greatest good",
    "start": "234720",
    "end": "239819"
  },
  {
    "text": "positive psychology is not only that right positive psychology like I said it's more about thriving and how can you",
    "start": "239819",
    "end": "246959"
  },
  {
    "text": "actually figure out how to be the most successful and the happiest and the the",
    "start": "246959",
    "end": "252720"
  },
  {
    "text": "best you can be so",
    "start": "252720",
    "end": "258079"
  },
  {
    "text": "um let's talk a little bit more about this so positive psychology or the psychology",
    "start": "259380",
    "end": "265800"
  },
  {
    "start": "260000",
    "end": "450000"
  },
  {
    "text": "of thriving is is really really not a New Concept um so Aristotle talked about this in",
    "start": "265800",
    "end": "272460"
  },
  {
    "text": "terms of eudemonia which is essentially the same thing in aristolian ethics the",
    "start": "272460",
    "end": "279600"
  },
  {
    "text": "condition of human flourishing or of living well is how this is defined right so again not a very New Concept I am 100",
    "start": "279600",
    "end": "287280"
  },
  {
    "text": "sure that other cultures had had similar Concepts but what happened in Western",
    "start": "287280",
    "end": "293520"
  },
  {
    "text": "um in the Western World right is is the field of psychology emerged a lot of the",
    "start": "293520",
    "end": "300180"
  },
  {
    "text": "emphasis of Psychology was on studying mental illness right and essentially if",
    "start": "300180",
    "end": "306180"
  },
  {
    "text": "you look at the top of this image traditional psychology is about like dealing figuring out how to deal with",
    "start": "306180",
    "end": "312419"
  },
  {
    "text": "mental illness and bringing people to a baseline where they're high functioning and doing well and that's obviously",
    "start": "312419",
    "end": "319620"
  },
  {
    "text": "super critical and that's something that we must pay attention to and must research but after a while some people",
    "start": "319620",
    "end": "327240"
  },
  {
    "text": "started to realize that you know we're really ignoring a lot of what happens to",
    "start": "327240",
    "end": "332520"
  },
  {
    "text": "the people that are already starting from a baseline that are not dealing with mental illness perhaps or even have",
    "start": "332520",
    "end": "338759"
  },
  {
    "text": "dealt with their mental illness and now want to go beyond it and that's really what positive psychology is about",
    "start": "338759",
    "end": "346400"
  },
  {
    "text": "so the founders of um of modern day positive psychology Martin",
    "start": "346580",
    "end": "354960"
  },
  {
    "text": "Seligman and mihili chicken me highly and I apologize for mispronouncing his",
    "start": "354960",
    "end": "360660"
  },
  {
    "text": "name I'm sure everybody does I tried um so what they talk about I put down",
    "start": "360660",
    "end": "366120"
  },
  {
    "text": "here on the slide you can read for yourself psychology is also the study of strength and virtue it is about work",
    "start": "366120",
    "end": "373080"
  },
  {
    "text": "education inside love growth and play um it is it tries to adapt what is best",
    "start": "373080",
    "end": "379380"
  },
  {
    "text": "in the scientific method to the unique problems that human behavior presents in all its complexity",
    "start": "379380",
    "end": "385440"
  },
  {
    "text": "and so that really gets to the root of what we want to talk about here and one",
    "start": "385440",
    "end": "390539"
  },
  {
    "text": "of the things that you'll see here is he talks specifically about the scientific method so",
    "start": "390539",
    "end": "396180"
  },
  {
    "text": "I am computer Scientist by training um and you know I I read for fun I read",
    "start": "396180",
    "end": "403160"
  },
  {
    "text": "psychology research and other behavioral research and if you've done this you",
    "start": "403160",
    "end": "408720"
  },
  {
    "text": "will probably note that a lot of the studies say things like the majority of people or there is a correlation between",
    "start": "408720",
    "end": "414720"
  },
  {
    "text": "certain behavior and what's really important to understand is that",
    "start": "414720",
    "end": "419819"
  },
  {
    "text": "that doesn't mean that everybody behaves a certain way as I'm sure you have figured out people are very complicated",
    "start": "419819",
    "end": "425880"
  },
  {
    "text": "and not everybody behaves a certain way and so even the things that we're talking about here today some of them",
    "start": "425880",
    "end": "432479"
  },
  {
    "text": "may apply to you some of them may be not as much and and that's okay what's",
    "start": "432479",
    "end": "438720"
  },
  {
    "text": "really more important or more interesting is you know reflecting on that trying it out trying some of these",
    "start": "438720",
    "end": "445080"
  },
  {
    "text": "techniques and then seeing what works for you",
    "start": "445080",
    "end": "449360"
  },
  {
    "text": "so I talked just with this backdrop let's talk a little bit about how all of",
    "start": "452099",
    "end": "457979"
  },
  {
    "text": "this applies to work right because we're here this is a professional conference we want to think about how that applies",
    "start": "457979",
    "end": "465360"
  },
  {
    "text": "to to work and you know it was already mentioned before and this quote that I",
    "start": "465360",
    "end": "470759"
  },
  {
    "text": "gave yes there is this is actually predictive of how well people thrive at work and how well teams function",
    "start": "470759",
    "end": "476880"
  },
  {
    "text": "together so if you're an engineer who works on my team and you come to me and you say you",
    "start": "476880",
    "end": "484139"
  },
  {
    "text": "want to be a manager then I will say interesting let's have a little chat and",
    "start": "484139",
    "end": "489780"
  },
  {
    "text": "I will ask you why you want to be a manager if you tell me it's because you haven't been coding for a while that's",
    "start": "489780",
    "end": "496560"
  },
  {
    "text": "not the correct answer so really managing is a different kind",
    "start": "496560",
    "end": "502680"
  },
  {
    "text": "of job and um it really um requires people to spend a lot more time",
    "start": "502680",
    "end": "509819"
  },
  {
    "text": "thinking about all of these Dynamics between people which I find endlessly fascinating but perhaps it's not for",
    "start": "509819",
    "end": "515700"
  },
  {
    "text": "everyone so if you are a manager you may have seen some of these models",
    "start": "515700",
    "end": "521419"
  },
  {
    "text": "some several models and and including the ones that I put up here and",
    "start": "521419",
    "end": "528540"
  },
  {
    "text": "they actually really tie into a lot of what we're talking about that comes out of the the psychology research",
    "start": "528540",
    "end": "534899"
  },
  {
    "text": "um so the one on the left talks about individuals and you see here the x-axis's attitude the y-axis is",
    "start": "534899",
    "end": "542459"
  },
  {
    "text": "performance and capability and it essentially models how you can think about how well somebody is doing in",
    "start": "542459",
    "end": "549420"
  },
  {
    "text": "their current role right are there you know are they challenged too much perhaps are they our star which is the",
    "start": "549420",
    "end": "556800"
  },
  {
    "text": "top right corner which is what we're striving towards so um you can think for yourself where you",
    "start": "556800",
    "end": "562500"
  },
  {
    "text": "fit in this and if you're a manager you definitely spend time thinking about your team and where they fit on these",
    "start": "562500",
    "end": "568440"
  },
  {
    "text": "axes what's really important is that this actually also applies to teams so some",
    "start": "568440",
    "end": "574860"
  },
  {
    "text": "of you may have seen this model here on the right which is about teams and how",
    "start": "574860",
    "end": "579899"
  },
  {
    "text": "they come together how they form how they go through a period of striving",
    "start": "579899",
    "end": "585180"
  },
  {
    "text": "Strife which is the storming phase here where everybody kind of tries to figure",
    "start": "585180",
    "end": "591480"
  },
  {
    "text": "out what is my role in this team and who kind of calls the shots and and where do",
    "start": "591480",
    "end": "597480"
  },
  {
    "text": "I fit in and then they come together and they they are they finally become High",
    "start": "597480",
    "end": "603300"
  },
  {
    "text": "performing teams and you know where they can execute well deliver impact before",
    "start": "603300",
    "end": "609420"
  },
  {
    "text": "they finally adjourn so these models again are models that",
    "start": "609420",
    "end": "614880"
  },
  {
    "text": "are often taught in leadership training and you may have seen them and they're actually quite well backed by by some of",
    "start": "614880",
    "end": "621480"
  },
  {
    "text": "the research that we're talking about here I put a quote here at the top of the",
    "start": "621480",
    "end": "626940"
  },
  {
    "text": "slide in part because I want to put in a plug for a book that I read that really inspired me",
    "start": "626940",
    "end": "633380"
  },
  {
    "text": "the book is called The Happiness Advantage how a positive brain fuels",
    "start": "633380",
    "end": "638399"
  },
  {
    "text": "success in work and life I really had fun reading this book so I recommended and the quote is happiness is not the",
    "start": "638399",
    "end": "644880"
  },
  {
    "text": "belief that we don't need to change it is the realization that we can",
    "start": "644880",
    "end": "650220"
  },
  {
    "text": "so please take a look if you're inspired by this take a look at this book there's a lot to learn there",
    "start": "650220",
    "end": "657980"
  },
  {
    "start": "657000",
    "end": "700000"
  },
  {
    "text": "so if you read about positive psychology you'll find that you know different",
    "start": "658800",
    "end": "665459"
  },
  {
    "text": "people kind of try to get their heads around the different dimensions of how",
    "start": "665459",
    "end": "670620"
  },
  {
    "text": "all of this fits together and there are so there are different ways of breaking this down and breaking",
    "start": "670620",
    "end": "676380"
  },
  {
    "text": "down these dimensions one of those models is called Perma and that's a pretty popular one",
    "start": "676380",
    "end": "684120"
  },
  {
    "text": "uh so I will talk about it here in this context um Perma like I said is only one of the",
    "start": "684120",
    "end": "690720"
  },
  {
    "text": "ways you can think about the different axes that come into play here um but it I find it to be a useful one",
    "start": "690720",
    "end": "698640"
  },
  {
    "text": "so let's stick with that for now so what is Perma Perma stands for",
    "start": "698640",
    "end": "703880"
  },
  {
    "start": "700000",
    "end": "798000"
  },
  {
    "text": "positive emotion engagement relationships meaning and",
    "start": "703880",
    "end": "709320"
  },
  {
    "text": "accomplishments so we'll talk about each of these in turn and we'll talk a little bit about",
    "start": "709320",
    "end": "715700"
  },
  {
    "text": "how they what they mean and how what you can do to put yourself in a position to",
    "start": "715700",
    "end": "721260"
  },
  {
    "text": "get them right as you may guess and this is a good",
    "start": "721260",
    "end": "726600"
  },
  {
    "text": "thing Perma predicts the flourishing of communities organizations and Nations",
    "start": "726600",
    "end": "731720"
  },
  {
    "text": "and it has a positive correlation with physical health job satisfaction life",
    "start": "731720",
    "end": "737519"
  },
  {
    "text": "satisfaction and so forth so this is really important stuff right so um now if you're a cynic then you will",
    "start": "737519",
    "end": "745200"
  },
  {
    "text": "come and you will say okay great so if I have positive emotions and great meaning and a lot of accomplishments then I will",
    "start": "745200",
    "end": "751440"
  },
  {
    "text": "be successful which seems backwards right so I'm here to tell you it's not",
    "start": "751440",
    "end": "756899"
  },
  {
    "text": "quite that simple right so there are ways that we can actually work to put ourselves in a better position to",
    "start": "756899",
    "end": "763560"
  },
  {
    "text": "have all of these things that are mentioned here that's what we'll be talking about um and then we'll talk a little bit also",
    "start": "763560",
    "end": "770459"
  },
  {
    "text": "about willpower because some of the things that you need to do in order to put yourself in a better position to get",
    "start": "770459",
    "end": "775620"
  },
  {
    "text": "these things is you need to have willpower and you can learn that too so it's it's",
    "start": "775620",
    "end": "781320"
  },
  {
    "text": "sort of twiddles all the way down um one quick note uh if you I will",
    "start": "781320",
    "end": "788700"
  },
  {
    "text": "publish the slides with the speaker notes and in the speaker notes I have references so if you want to do more",
    "start": "788700",
    "end": "794579"
  },
  {
    "text": "reading afterwards I put references in in there as well",
    "start": "794579",
    "end": "800000"
  },
  {
    "start": "798000",
    "end": "846000"
  },
  {
    "text": "okay so learning positivity when I started on this journey I was definitely",
    "start": "800459",
    "end": "806639"
  },
  {
    "text": "not an optimist I don't know if I guess I'm more optimistic today that's for sure",
    "start": "806639",
    "end": "811980"
  },
  {
    "text": "um I didn't necessarily always have a positive outlook and one of the key things here is that this is something",
    "start": "811980",
    "end": "818160"
  },
  {
    "text": "you can train and you can learn it is not true that um you know we are we you know if you're",
    "start": "818160",
    "end": "825180"
  },
  {
    "text": "pessimist and you're doomed to a life of pessimism if that's something that you want to work on you can actually it's",
    "start": "825180",
    "end": "831779"
  },
  {
    "text": "going to require work and time and investment but it can be learned and then as we saw before it puts you in a",
    "start": "831779",
    "end": "838800"
  },
  {
    "text": "better position for these other effects which then in turn set you up for",
    "start": "838800",
    "end": "844200"
  },
  {
    "text": "success okay let's Dive In",
    "start": "844200",
    "end": "850139"
  },
  {
    "start": "846000",
    "end": "943000"
  },
  {
    "text": "positive emotion what is positive emotions so think about positive emotion",
    "start": "850139",
    "end": "856560"
  },
  {
    "text": "um that can mean obviously a lot of things what it doesn't necessarily only mean is you know",
    "start": "856560",
    "end": "864360"
  },
  {
    "text": "being you know ignoring everything bad that's going on and just I don't know giggling and having fun and getting",
    "start": "864360",
    "end": "870660"
  },
  {
    "text": "drunk right that's not necessarily what this means positive emotion is can be a range of",
    "start": "870660",
    "end": "876899"
  },
  {
    "text": "different kinds of emotions as we'll see but I'll just start with a very small example it can be small things too right",
    "start": "876899",
    "end": "884399"
  },
  {
    "text": "so for myself when I have a difficult day ahead at work I have a lot of",
    "start": "884399",
    "end": "891060"
  },
  {
    "text": "meetings and sometimes I have you know presentations that are perhaps tricky or or something that I'm not necessarily",
    "start": "891060",
    "end": "897720"
  },
  {
    "text": "looking forward to um when I after I drop off my daughter at school I think about two things",
    "start": "897720",
    "end": "904380"
  },
  {
    "text": "number one my commute and number two breakfast and so both of those actually put me in",
    "start": "904380",
    "end": "911160"
  },
  {
    "text": "a good frame of mind the commute it's a 15-minute drive and it's literally the only time of the day where nobody",
    "start": "911160",
    "end": "916980"
  },
  {
    "text": "expects anything from me so I actually really like it and then breakfast I love to eat so you know so",
    "start": "916980",
    "end": "925260"
  },
  {
    "text": "those are the two things that I'm like okay let's just think about those two things I'm gonna enjoy my commute I'm",
    "start": "925260",
    "end": "930660"
  },
  {
    "text": "gonna enjoy breakfast and then I will tackle the day and just that um small",
    "start": "930660",
    "end": "936600"
  },
  {
    "text": "um you know reflection helps me um so maybe it's something that you can",
    "start": "936600",
    "end": "941940"
  },
  {
    "text": "try for yourself Okay so",
    "start": "941940",
    "end": "947160"
  },
  {
    "start": "943000",
    "end": "1069000"
  },
  {
    "text": "positive emotion what is it um the way it's again like if you read the literature different people you know",
    "start": "947160",
    "end": "953639"
  },
  {
    "text": "name different kinds of words but you can think about sort of the spectrum of positive emotions Joy gratitude Serenity",
    "start": "953639",
    "end": "959880"
  },
  {
    "text": "interest Hope Pride Amusement inspiration awe and love",
    "start": "959880",
    "end": "966180"
  },
  {
    "text": "um and so that's that obviously runs the gamut of everything that you might think about",
    "start": "966180",
    "end": "973199"
  },
  {
    "text": "um and one of the things that I want you to reflect for yourselves is you know sometimes I ask people do you have you",
    "start": "973199",
    "end": "979680"
  },
  {
    "text": "know how do you feel about work do you get positive emotions at work and you know depending on who you talk to a",
    "start": "979680",
    "end": "987120"
  },
  {
    "text": "lot of people will say oh I don't know I guess I you know sometimes but I would",
    "start": "987120",
    "end": "992639"
  },
  {
    "text": "posit that a lot of us actually get more of this at work than we than we even admit to ourselves I'll give you another",
    "start": "992639",
    "end": "999839"
  },
  {
    "text": "example for myself you know now that we finished breakfast one of the projects that I worked on a",
    "start": "999839",
    "end": "1006800"
  },
  {
    "text": "couple years ago is it was actually a very difficult project we tried for a couple years to get it off the ground it",
    "start": "1006800",
    "end": "1012860"
  },
  {
    "text": "was difficult it involved a variety of different teams it was technically very challenging and so it was easy to just",
    "start": "1012860",
    "end": "1019759"
  },
  {
    "text": "kind of give up and and throw hands in the air and we finally managed to get it off the ground",
    "start": "1019759",
    "end": "1026418"
  },
  {
    "text": "um and what I mean by that is we came together we had a credible plan um we you know we got the different",
    "start": "1026419",
    "end": "1033438"
  },
  {
    "text": "teams bought into it we had milestones and and we kind of knew yes if we do",
    "start": "1033439",
    "end": "1039140"
  },
  {
    "text": "this and we stick to it we can actually make progress here in land testing and what happens then is like you get in a",
    "start": "1039140",
    "end": "1047178"
  },
  {
    "text": "room and and you see once you start hitting the first Milestones you see how people feel right and and they're just",
    "start": "1047179",
    "end": "1053480"
  },
  {
    "text": "excited and they're proud that we finally managed to do this and they have",
    "start": "1053480",
    "end": "1058700"
  },
  {
    "text": "a range of positive emotions and the energy in the room is just really good so",
    "start": "1058700",
    "end": "1063799"
  },
  {
    "text": "reflect for yourselves maybe you get more of this at work than you already thought you did",
    "start": "1063799",
    "end": "1069630"
  },
  {
    "start": "1069000",
    "end": "1174000"
  },
  {
    "text": "[Applause] um so now the question is what can you do to have more positive emotions right",
    "start": "1069630",
    "end": "1076760"
  },
  {
    "text": "you can then work on a project and get lucky that we finally or you know work hard and finally get it off the ground but if you um if you if you again read a",
    "start": "1076760",
    "end": "1086720"
  },
  {
    "text": "little bit um the the literature one of the most concrete things that people advise is a",
    "start": "1086720",
    "end": "1094100"
  },
  {
    "text": "practice of gratitude okay so what does this mean gratitude uh means you sit",
    "start": "1094100",
    "end": "1101240"
  },
  {
    "text": "back and you think about what is it that I'm grateful for it's pretty simple right so you know people say write down",
    "start": "1101240",
    "end": "1109039"
  },
  {
    "text": "three things that you're grateful for every day right on at the end of the day reflect back what am I grateful for okay",
    "start": "1109039",
    "end": "1117280"
  },
  {
    "text": "people recommend writing gratitude letters to people even if you don't send them like write down why you're grateful",
    "start": "1117280",
    "end": "1123380"
  },
  {
    "text": "for them um so I don't do this super explicitly myself",
    "start": "1123380",
    "end": "1128840"
  },
  {
    "text": "but I do spend a lot of time thinking about like on my morning run or you know the sun is beautiful and things like",
    "start": "1128840",
    "end": "1134900"
  },
  {
    "text": "that so there's a lot of research going on right now",
    "start": "1134900",
    "end": "1141080"
  },
  {
    "text": "um in this and I read this one paper where they were trying to figure out is there you know I'm skeptic too is this",
    "start": "1141080",
    "end": "1148400"
  },
  {
    "text": "causal or is there a correlation there's definitely a very positive correlation between gratitude and people having",
    "start": "1148400",
    "end": "1155600"
  },
  {
    "text": "positive emotions and feeling better um the research is still torn right for",
    "start": "1155600",
    "end": "1162620"
  },
  {
    "text": "sure it doesn't hurt to have gratefulness uh gratitude but it's not entirely clear if this is fully causal",
    "start": "1162620",
    "end": "1169100"
  },
  {
    "text": "but it doesn't hurt so why not give it a try",
    "start": "1169100",
    "end": "1175700"
  },
  {
    "start": "1174000",
    "end": "1529000"
  },
  {
    "text": "um Okay so let me tell you another thing so I",
    "start": "1175700",
    "end": "1181400"
  },
  {
    "text": "talked about you know when I when I have a hard day ahead of work I think about my commute and breakfast",
    "start": "1181400",
    "end": "1188620"
  },
  {
    "text": "and this is actually turns out when I was reading the Happiness Advantage which is the book I just recommended",
    "start": "1188620",
    "end": "1195160"
  },
  {
    "text": "they had a study on this which I thought found fascinating that sort of validated",
    "start": "1195160",
    "end": "1200600"
  },
  {
    "text": "what I was doing intuitively and the study said they had two groups of",
    "start": "1200600",
    "end": "1205640"
  },
  {
    "text": "doctors and the task was that doctors had to diagnose a patient so they were like given a file with like symptoms and",
    "start": "1205640",
    "end": "1212539"
  },
  {
    "text": "background and whatever else and they had to come to a diagnosis and they had",
    "start": "1212539",
    "end": "1217760"
  },
  {
    "text": "the control group and the and you know the study group and they measured how",
    "start": "1217760",
    "end": "1223940"
  },
  {
    "text": "quickly they would reach the correct conclusion and so the control group did",
    "start": "1223940",
    "end": "1230120"
  },
  {
    "text": "this the way they normally would and the study group the only difference was that they were given candies",
    "start": "1230120",
    "end": "1235700"
  },
  {
    "text": "ahead of time okay so they were giving candies but they could they weren't even allowed to eat them because they were",
    "start": "1235700",
    "end": "1241340"
  },
  {
    "text": "like we don't want to mess with your blood sugar because that's going to mess with our studies so here's your candy don't eat it and now do this task and so",
    "start": "1241340",
    "end": "1249320"
  },
  {
    "text": "the people that got the candy and didn't eat it actually perform much much better",
    "start": "1249320",
    "end": "1254600"
  },
  {
    "text": "why the hypothesis is because they were in a positive frame of mind so",
    "start": "1254600",
    "end": "1260600"
  },
  {
    "text": "the answer is not eat candy all the time it's more",
    "start": "1260600",
    "end": "1265880"
  },
  {
    "text": "complicated than that but I think the takeaway really is that even small things can set you up for for success",
    "start": "1265880",
    "end": "1273280"
  },
  {
    "text": "the flip side of that is certainly also true and I'm sure many of you have have experienced that which is",
    "start": "1273280",
    "end": "1280520"
  },
  {
    "text": "you know when when when you rattle somebody like you know if somebody is about to give a presentation and you say",
    "start": "1280520",
    "end": "1287900"
  },
  {
    "text": "oh you're probably going to mess it up and you're such a terrible speaker they're probably not going to do very well right so I had uh this happened to",
    "start": "1287900",
    "end": "1296179"
  },
  {
    "text": "me recently I did like a mini experiment uh with my colleagues I was sitting down",
    "start": "1296179",
    "end": "1301760"
  },
  {
    "text": "for lunch in the cafeteria and this colleague approached me whom I hadn't seen in a couple years you know because",
    "start": "1301760",
    "end": "1308179"
  },
  {
    "text": "kovid and um he asked me how I was doing and I was",
    "start": "1308179",
    "end": "1315080"
  },
  {
    "text": "like right in the middle of this difficult thing um that I was trying to figure out and I",
    "start": "1315080",
    "end": "1320900"
  },
  {
    "text": "said I'm doing fine but right now I'm struggling with this one thing and this person was pretty dismissive right it",
    "start": "1320900",
    "end": "1327320"
  },
  {
    "text": "was like ah you know you shouldn't you shouldn't say that that's hard and it's really important and you should be able",
    "start": "1327320",
    "end": "1332960"
  },
  {
    "text": "to do it basically and it made me feel not very good obviously and the rest of the",
    "start": "1332960",
    "end": "1338240"
  },
  {
    "text": "conversation didn't go very well right okay so this person left and then I sat",
    "start": "1338240",
    "end": "1344059"
  },
  {
    "text": "there and I still hadn't finished my lunch and another person showed up and the second person is actually somebody",
    "start": "1344059",
    "end": "1349220"
  },
  {
    "text": "who's like quite intimidating um often but he sat down started talking to me",
    "start": "1349220",
    "end": "1356840"
  },
  {
    "text": "and I'm like maybe I overreacted like maybe I I didn't do this right in this with this",
    "start": "1356840",
    "end": "1363559"
  },
  {
    "text": "other person so I'm gonna say the exact same thing now so this person sat down and said how are you doing and I'm like",
    "start": "1363559",
    "end": "1369740"
  },
  {
    "text": "exact same thing I'm doing fine but right now I'm struggling with this and the second person was like super",
    "start": "1369740",
    "end": "1376220"
  },
  {
    "text": "supportive immediately and like built that Rapport between us and and tried to help me puzzle through it and",
    "start": "1376220",
    "end": "1383179"
  },
  {
    "text": "made all the difference in the world as you may imagine right um so why is this important it's",
    "start": "1383179",
    "end": "1389179"
  },
  {
    "text": "important because what you say to your colleagues really really matters right",
    "start": "1389179",
    "end": "1394940"
  },
  {
    "text": "like it's not just it's as a leader obviously it matters what we say to our teams",
    "start": "1394940",
    "end": "1400820"
  },
  {
    "text": "um but even as every you know everybody who we interact with how we put them the",
    "start": "1400820",
    "end": "1406820"
  },
  {
    "text": "frame of mind we put them in really really makes a big difference okay so let's talk a little bit about",
    "start": "1406820",
    "end": "1413600"
  },
  {
    "text": "what kinds of things you can do to induce positive emotions so we talked about candy that's probably a very",
    "start": "1413600",
    "end": "1419480"
  },
  {
    "text": "short-term solution if you want longer term Solutions um one of the running themes you will",
    "start": "1419480",
    "end": "1425299"
  },
  {
    "text": "see here today is exercise and meditation sleeping well eating healthy that sort",
    "start": "1425299",
    "end": "1432679"
  },
  {
    "text": "of thing and it's actually it just shows up over and",
    "start": "1432679",
    "end": "1437720"
  },
  {
    "text": "over and over and over again right so you might say yes I kind of already knew",
    "start": "1437720",
    "end": "1444380"
  },
  {
    "text": "this was good for me maybe what you didn't know is that this will actually help you have more positive emotions and",
    "start": "1444380",
    "end": "1450799"
  },
  {
    "text": "and all of these other things that we're talking about and there those things are actually predictors of success right so",
    "start": "1450799",
    "end": "1458659"
  },
  {
    "text": "you know I happen to like exercise as much as I like breakfast and",
    "start": "1458659",
    "end": "1464960"
  },
  {
    "text": "we'll talk about meditation later but these are the kinds of things that will show up again over and over and over",
    "start": "1464960",
    "end": "1471620"
  },
  {
    "text": "again using your strengths is an interesting one that also shows up in this",
    "start": "1471620",
    "end": "1477320"
  },
  {
    "text": "literature a lot so using your strengths is basically like what are your character strengths what are you good at",
    "start": "1477320",
    "end": "1485419"
  },
  {
    "text": "um intuitively they are surveys out there that you can take for free and",
    "start": "1485419",
    "end": "1490820"
  },
  {
    "text": "essentially what what we're what's being found is that if people do the things that they're already like naturally",
    "start": "1490820",
    "end": "1497120"
  },
  {
    "text": "gravitate to they will feel better it's not super unintuitive but you know go",
    "start": "1497120",
    "end": "1503179"
  },
  {
    "text": "figure out what your strengths are I went and took one of those strings finders in fact I had to do it twice",
    "start": "1503179",
    "end": "1508520"
  },
  {
    "text": "because I forgot what my strengths were and so I had to do it again it turns out my biggest",
    "start": "1508520",
    "end": "1514220"
  },
  {
    "text": "strengths is showing love which I haven't quite figured out how to apply that to work yet but I assume it's like",
    "start": "1514220",
    "end": "1520280"
  },
  {
    "text": "I don't know I can only guess like showing appreciation for other people and and celebrating their success so",
    "start": "1520280",
    "end": "1528399"
  },
  {
    "start": "1529000",
    "end": "1551000"
  },
  {
    "text": "let's talk about engagement this is this engagement is one of my favorite topics",
    "start": "1531320",
    "end": "1536419"
  },
  {
    "text": "um even though I have to say this name again so engagement is being one with",
    "start": "1536419",
    "end": "1542059"
  },
  {
    "text": "the music is what it's sometimes called it's like the steeper happiness there like you're really there you're really",
    "start": "1542059",
    "end": "1548200"
  },
  {
    "text": "engaged and with what you're doing right so this is such an important concept",
    "start": "1548200",
    "end": "1555260"
  },
  {
    "start": "1551000",
    "end": "1591000"
  },
  {
    "text": "that it sort of spawned this whole subfield that you may have heard of um it's called flow it's the same kind",
    "start": "1555260",
    "end": "1562520"
  },
  {
    "text": "of concept like losing track of time being right there being completely absorbed by what you're doing right so",
    "start": "1562520",
    "end": "1570039"
  },
  {
    "text": "the credit for first studying this goes again to Chick sent me highly",
    "start": "1570039",
    "end": "1575900"
  },
  {
    "text": "sorry I really tried it's a very difficult name for me to pronounce but in any case he you will see this all",
    "start": "1575900",
    "end": "1582559"
  },
  {
    "text": "over the books if you read books like this shows up over and over again how do you put yourself in a position where you",
    "start": "1582559",
    "end": "1588679"
  },
  {
    "text": "are completely absorbed by your work now reflect on that a little bit when was the last time you were completely",
    "start": "1588679",
    "end": "1594620"
  },
  {
    "start": "1591000",
    "end": "1700000"
  },
  {
    "text": "absorbed by what you were doing for me it happens to be right now because you know I'm I I love doing this kind of",
    "start": "1594620",
    "end": "1601159"
  },
  {
    "text": "thing but what people found is that there is this axis you know if you look",
    "start": "1601159",
    "end": "1607100"
  },
  {
    "text": "at the x x axis being skills and the y-axis being challenges",
    "start": "1607100",
    "end": "1612200"
  },
  {
    "text": "there is this I guess they call it a flow channel right so there's this this area in the middle that if you're in The",
    "start": "1612200",
    "end": "1619340"
  },
  {
    "text": "Sweet Spot area then you can really Thrive and you can",
    "start": "1619340",
    "end": "1624980"
  },
  {
    "text": "you know lose track of time be engaged and also learn this is also the The Sweet Spot for learning so you don't",
    "start": "1624980",
    "end": "1631520"
  },
  {
    "text": "want to be too much on the boredom access and too much on the anxiety axis right now this is a really good time to",
    "start": "1631520",
    "end": "1639020"
  },
  {
    "text": "talk about job and job change right as you think about",
    "start": "1639020",
    "end": "1644720"
  },
  {
    "text": "if you're you know for your job do you fall most of the time within that flow",
    "start": "1644720",
    "end": "1651320"
  },
  {
    "text": "Channel um what happens sometimes to people is when they change jobs you know they're",
    "start": "1651320",
    "end": "1656539"
  },
  {
    "text": "more on the anxiety um side and that's okay right like they're being well pushed out of their comfort zone and maybe they can catch up",
    "start": "1656539",
    "end": "1662720"
  },
  {
    "text": "but if you're constantly on that side then it's really time to change something right whereas if you're always",
    "start": "1662720",
    "end": "1670039"
  },
  {
    "text": "all the time bored that's that's also the time to change something and I feel like oftentimes people don't think about",
    "start": "1670039",
    "end": "1676279"
  },
  {
    "text": "this very explicitly but once they see something like this they're like oh yeah that actually kind of makes sense so if",
    "start": "1676279",
    "end": "1682039"
  },
  {
    "text": "you're a leader in our organizations you know we see this all the time where people uh you know",
    "start": "1682039",
    "end": "1688700"
  },
  {
    "text": "become more comfortable then they become complacent or bored or whatever you really need to push them out of their",
    "start": "1688700",
    "end": "1694460"
  },
  {
    "text": "comfort zones a little bit and then they end up being happier and more productive",
    "start": "1694460",
    "end": "1700299"
  },
  {
    "start": "1700000",
    "end": "1729000"
  },
  {
    "text": "Okay so what do you do to get into this state of",
    "start": "1701059",
    "end": "1706400"
  },
  {
    "text": "flow a lot of the things that we've already talked about using your caring character",
    "start": "1706400",
    "end": "1712400"
  },
  {
    "text": "strengths doing the things you love meditate and exercise",
    "start": "1712400",
    "end": "1719480"
  },
  {
    "text": "spend time in nature so I hope that all of you already love to exercise and love to meditate if not this is your",
    "start": "1719480",
    "end": "1727100"
  },
  {
    "text": "opportunity let's talk a little bit about",
    "start": "1727100",
    "end": "1732320"
  },
  {
    "start": "1729000",
    "end": "1741000"
  },
  {
    "text": "relationships so relationships you know obviously we're talking about positive",
    "start": "1732320",
    "end": "1739279"
  },
  {
    "text": "relationships here and this has been of course for the last",
    "start": "1739279",
    "end": "1744559"
  },
  {
    "text": "couple of years a very difficult topic for many of us because it's been so isolating you know we're back together",
    "start": "1744559",
    "end": "1750740"
  },
  {
    "text": "in person for the first time at a conference a lot of us still work from home you know we're starting to come",
    "start": "1750740",
    "end": "1756799"
  },
  {
    "text": "back into the office and you know a lot of us are seeing you know far away loved",
    "start": "1756799",
    "end": "1762080"
  },
  {
    "text": "ones for the first time again in person so that's this has been really hard it's very clear that",
    "start": "1762080",
    "end": "1769480"
  },
  {
    "text": "positive relationships are a good predictor of pretty much everything in life right not just being successful at",
    "start": "1769480",
    "end": "1776179"
  },
  {
    "text": "work um longevity is one of them good health is another so",
    "start": "1776179",
    "end": "1782140"
  },
  {
    "text": "if there's anything you can take away from this talk if you forget everything else positive relationships are very",
    "start": "1782140",
    "end": "1788840"
  },
  {
    "text": "critical to success that's just that's pretty well understood um",
    "start": "1788840",
    "end": "1794539"
  },
  {
    "text": "so let's talk about one thing uh",
    "start": "1794539",
    "end": "1801278"
  },
  {
    "start": "1796000",
    "end": "1981000"
  },
  {
    "text": "why does this matter to this talk here right so oftentimes when when I talk to",
    "start": "1801919",
    "end": "1807020"
  },
  {
    "text": "people they're like yeah you know I have my group of friends and I have my family super important I get it but what about",
    "start": "1807020",
    "end": "1814100"
  },
  {
    "text": "your relationships at work I remember when I first started out you",
    "start": "1814100",
    "end": "1820700"
  },
  {
    "text": "know in my first jobs I remember I was definitely more in the anxiety part of this flow chart that that we saw and I",
    "start": "1820700",
    "end": "1828080"
  },
  {
    "text": "just could not fathom hanging out with uh with friends sorry with with colleagues outside of talking about work",
    "start": "1828080",
    "end": "1835399"
  },
  {
    "text": "right I would show up at work we would have work conversations but I couldn't fathom uh you know going beyond that and",
    "start": "1835399",
    "end": "1843440"
  },
  {
    "text": "I think over time what I've learned is that and also what I read in the",
    "start": "1843440",
    "end": "1848539"
  },
  {
    "text": "literature is that our brains really don't make a difference between uh people that we know from conferences or",
    "start": "1848539",
    "end": "1854840"
  },
  {
    "text": "from the dog park and people that we know from work so it's actually really important to to",
    "start": "1854840",
    "end": "1861260"
  },
  {
    "text": "treat those relationships um with care and that doesn't mean that",
    "start": "1861260",
    "end": "1866779"
  },
  {
    "text": "we're going to be friends with everybody that we work with I suspect that's true for many of us but it's probably also",
    "start": "1866779",
    "end": "1873080"
  },
  {
    "text": "true for many of us that we will find people at work that we connect with and that are truly our friends and and that",
    "start": "1873080",
    "end": "1880700"
  },
  {
    "text": "we have important relationships with one story",
    "start": "1880700",
    "end": "1886220"
  },
  {
    "text": "um that may resonate with some of you is that I you know we also work from home",
    "start": "1886220",
    "end": "1892700"
  },
  {
    "text": "at Google for a very long time and uh last year we had",
    "start": "1892700",
    "end": "1899059"
  },
  {
    "text": "a um we had like a summit and it was all online and we talked about work all day",
    "start": "1899059",
    "end": "1904159"
  },
  {
    "text": "long and then we actually a few of us um somebody had organized a get-together",
    "start": "1904159",
    "end": "1909679"
  },
  {
    "text": "in a park and this was with mostly people that are more senior than me so definitely pushing me a little bit out",
    "start": "1909679",
    "end": "1916100"
  },
  {
    "text": "of my comfort zone but many of whom I knew and I signed up I'm like I'm gonna go and then the day came and I'm like oh",
    "start": "1916100",
    "end": "1923120"
  },
  {
    "text": "I'm really kind of anxious about this I haven't seen anybody in person in ages and and I almost didn't go and of course",
    "start": "1923120",
    "end": "1930140"
  },
  {
    "text": "I went and it was so much fun it was like kind of ridiculous how happy I was afterwards",
    "start": "1930140",
    "end": "1936200"
  },
  {
    "text": "just to have seen people in person so I don't know if you had similar experiences to that but I was like on",
    "start": "1936200",
    "end": "1942860"
  },
  {
    "text": "Cloud9 it was kind of ridiculous I still talk about that day and night just like last week talked about talk with",
    "start": "1942860",
    "end": "1949399"
  },
  {
    "text": "somebody and I'm like I'll remember that day in the park it was so much fun so",
    "start": "1949399",
    "end": "1954620"
  },
  {
    "text": "again treat those things with care think about them and and just remember that",
    "start": "1954620",
    "end": "1961940"
  },
  {
    "text": "it's not you know it's also the impact that you have on the people around you right so if if you're open to uh you",
    "start": "1961940",
    "end": "1970340"
  },
  {
    "text": "know to treating these relationships with care it makes a big difference on on our teams as well",
    "start": "1970340",
    "end": "1976778"
  }
]