[
  {
    "text": "I'm Bob Sutton. I'm an organizational \npsychologist I've been at the Stanford  ",
    "start": "1680",
    "end": "6160"
  },
  {
    "text": "engineering school for more than 35 years studied \nall sorts of elements of leading innovation. How I  ",
    "start": "6160",
    "end": "12400"
  },
  {
    "text": "see myself as at that sort of uncomfortable \nintersection between the rigor of academia  ",
    "start": "12400",
    "end": "17599"
  },
  {
    "text": "and what it takes to get things done in the real \nworld. So in \"Leading Innovation\" I'm bringing you  ",
    "start": "17600",
    "end": "23520"
  },
  {
    "text": "ideas at the intersection between three things. \nFirst of all the best research we could find  ",
    "start": "23520",
    "end": "29840"
  },
  {
    "text": "about what leaders do to promote innovation \nthings like creating constructive conflict  ",
    "start": "29840",
    "end": "35280"
  },
  {
    "text": "psychological safety getting people to come up \nwith a wide range of ideas and then to pick the  ",
    "start": "35280",
    "end": "40800"
  },
  {
    "text": "best. The second part is to give you some of \nthe best case studies we can find from Apple,  ",
    "start": "40800",
    "end": "46640"
  },
  {
    "text": "IDEO, Pixar, Intel so you can learn from \nthe best practices and avoid the worst.  ",
    "start": "46640",
    "end": "53040"
  },
  {
    "text": "And then finally we bring you veteran executives \nso you can learn from Perry Klebahn who invented  ",
    "start": "53040",
    "end": "58960"
  },
  {
    "text": "the modern snowshoe now sort of a master \ninnovation teacher. \"Innovation is something that  ",
    "start": "58960",
    "end": "64479"
  },
  {
    "text": "the uncertainty can drive fear.\" Carl Liebert was \nCEO of the largest residential real estate company  ",
    "start": "64480",
    "end": "71840"
  },
  {
    "text": "\"change before you have to change once you get \nbehind it's really difficult to spend enough  ",
    "start": "72480",
    "end": "77600"
  },
  {
    "text": "money to catch up.\" Sylvia Acevedo her last job \nwas CEO of the girl scouts before that she was  ",
    "start": "77600",
    "end": "84000"
  },
  {
    "text": "a rocket scientist a tech executive. \"When people \ndidn't look for somebody like me I would focus on  ",
    "start": "84000",
    "end": "91120"
  },
  {
    "text": "the skills and then that allowed me in.\" Finally \nthe remarkable and imaginative venture capitalist,  ",
    "start": "91120",
    "end": "98160"
  },
  {
    "text": "Michael Dearing. \"You have to tell a story you \nhave to be great at making sense of the complex  ",
    "start": "98160",
    "end": "104160"
  },
  {
    "text": "reality for people.\" So in \"Leading Innovation\" by \nbringing you through a tour of those three things  ",
    "start": "104160",
    "end": "110880"
  },
  {
    "text": "punctuated by all sorts of different exercises is \nto help you understand the cases and companies you  ",
    "start": "110880",
    "end": "116880"
  },
  {
    "text": "can learn from the people I hope who can inspire \nyou and always we go back to what we think is the  ",
    "start": "116880",
    "end": "123759"
  },
  {
    "text": "best evidence about what good leaders do and how \nthey design their teams and their organizations.",
    "start": "123760",
    "end": "133600"
  }
]