[
  {
    "start": "0",
    "end": "14000"
  },
  {
    "text": "My name is Matt Campbell.",
    "start": "1899",
    "end": "3120"
  },
  {
    "text": "At D2L, I work as an Engineering Director.",
    "start": "3120",
    "end": "5420"
  },
  {
    "text": "I run the foundation divisions, and currently\nwe are responsible for optimizing our core",
    "start": "5420",
    "end": "10150"
  },
  {
    "text": "product to prepare it and enable it to run more\nsmoothly within AWS.",
    "start": "10150",
    "end": "14559"
  },
  {
    "start": "14000",
    "end": "28000"
  },
  {
    "text": "The mission of D2L is to change the way the\nworld learns. So, we're an EdTech company.",
    "start": "14559",
    "end": "18570"
  },
  {
    "text": "We produce learning management software, similar\nto what you would use if you took an online",
    "start": "18570",
    "end": "22619"
  },
  {
    "text": "course, or if your professor was putting documents\ninto the cloud for you to view when you were at home.",
    "start": "22620",
    "end": "28260"
  },
  {
    "text": "One of our chief business goals is to make sure that we are getting innovations out the door quickly.",
    "start": "28260",
    "end": "32419"
  },
  {
    "text": "Being all-in on AWS has allowed us to focus\non just one form of hosting for our software,",
    "start": "32460",
    "end": "39260"
  },
  {
    "text": "and it also provides us with a giant toolbox\nof ready-made solutions that we can use to",
    "start": "39270",
    "end": "44740"
  },
  {
    "text": "enable the solutions that our clients actually\nwant.",
    "start": "44740",
    "end": "47940"
  },
  {
    "text": "One of the benefits that we experienced that\nwas, maybe, not expected, was it actually",
    "start": "47960",
    "end": "51680"
  },
  {
    "text": "brought our development and our operation\ngroups closer together, really for the first",
    "start": "51690",
    "end": "55570"
  },
  {
    "text": "time, in order to figure out the best way\nto integrate ourselves with AWS.",
    "start": "55570",
    "end": "60200"
  },
  {
    "start": "60000",
    "end": "89000"
  },
  {
    "text": "So the three benefits that I look for in a\ncloud provider... for me, chiefly, number",
    "start": "60200",
    "end": "63680"
  },
  {
    "text": "one, I want them to be innovative.",
    "start": "63680",
    "end": "64780"
  },
  {
    "text": "I want them pushing the envelope on what technology\ncan do. That's giving me new tools in my toolbox",
    "start": "64780",
    "end": "69990"
  },
  {
    "text": "that I can use to help push the envelope on\nEdTech.",
    "start": "69990",
    "end": "72850"
  },
  {
    "text": "And AWS definitely hits the bill on that.",
    "start": "72850",
    "end": "75290"
  },
  {
    "text": "Year over year, they're releasing new technology\nall the time that we're always amazed to see...",
    "start": "75290",
    "end": "80950"
  },
  {
    "text": "the cool things that are coming out.",
    "start": "80950",
    "end": "81990"
  },
  {
    "text": "And it excites us, as developers, that we\nget to play with these tools and try to find",
    "start": "81990",
    "end": "85540"
  },
  {
    "text": "ways to integrate them together to produce\nthe things that our clients are going to love.",
    "start": "85540",
    "end": "89580"
  },
  {
    "start": "89000",
    "end": "112000"
  },
  {
    "text": "The second thing I'm looking for is ease of\nuse.",
    "start": "89580",
    "end": "91800"
  },
  {
    "text": "Day to day, I need my developers focused on\nsolving the business goals.",
    "start": "91800",
    "end": "96770"
  },
  {
    "text": "I don't want them spending heaps of cycles\ntrying to figure out, \"How do I run this tool?\"",
    "start": "96770",
    "end": "101409"
  },
  {
    "text": "\"How do I integrate these two pieces together?\"",
    "start": "101409",
    "end": "103490"
  },
  {
    "text": "The third thing I'm looking for is a bottom\nline.",
    "start": "103490",
    "end": "106090"
  },
  {
    "text": "So, I need to have all those pieces delivered\nto me but I need to be able to achieve my",
    "start": "106090",
    "end": "110799"
  },
  {
    "text": "budget needs.",
    "start": "110800",
    "end": "112040"
  },
  {
    "start": "112000",
    "end": "140000"
  },
  {
    "text": "By moving to AWS, we're consolidating down\non just one style of data center, which means",
    "start": "112040",
    "end": "117600"
  },
  {
    "text": "we no longer need to code multiple paths to\nsupport different environments; things are",
    "start": "117600",
    "end": "121909"
  },
  {
    "text": "more uniform.",
    "start": "121909",
    "end": "123340"
  },
  {
    "text": "When I deploy within Canada, and when I deploy\nwithin America, when I deploy within Europe,",
    "start": "123340",
    "end": "127420"
  },
  {
    "text": "we're getting the same results every single\ntime.",
    "start": "127420",
    "end": "129690"
  },
  {
    "text": "That means we have more time to spend on actually\nimproving our product, and less time on the plumbing.",
    "start": "129690",
    "end": "134720"
  }
]