[
  {
    "text": "all right well welcome and thank you for coming CGT will learn a senior principal",
    "start": "469",
    "end": "6690"
  },
  {
    "text": "engineer an uptake and i'm here with my",
    "start": "6690",
    "end": "12480"
  },
  {
    "text": "colleagues dan Collins and Brad boven and we're here today to talk about data",
    "start": "12480",
    "end": "18150"
  },
  {
    "text": "engineering the startup way so in terms of a quick agenda here of what we'll be",
    "start": "18150",
    "end": "23880"
  },
  {
    "text": "covering I'm going to talk through a brief introduction of uptake who we are",
    "start": "23880",
    "end": "29369"
  },
  {
    "text": "and what we do then gonna jump into some of the fun and interesting challenges that we run into on a day to day basis",
    "start": "29369",
    "end": "36950"
  },
  {
    "text": "I'm going to turn it over to Dan here who's going to talk through some of the interesting facts of life that we deal",
    "start": "36950",
    "end": "42629"
  },
  {
    "text": "with as a result of those challenges we're going to talk through how we've evolved both our platform and our",
    "start": "42629",
    "end": "48930"
  },
  {
    "text": "company over the previous few years to deal with some of these facts supplies and then finally we're going to close",
    "start": "48930",
    "end": "55050"
  },
  {
    "text": "with some lessons we've learned along the way hopefully some of which will help you along your journey as well so",
    "start": "55050",
    "end": "63420"
  },
  {
    "text": "if there are three things we want you to take away from this talk the first is if you're not familiar with uptake we want",
    "start": "63420",
    "end": "70170"
  },
  {
    "text": "you to hopefully walk away a little bit for more familiar with what we do and the problems that we solve hopefully",
    "start": "70170",
    "end": "76500"
  },
  {
    "text": "you'll learn a few things in terms of how AWS to make your lives easier and how it's made our lives easier and then",
    "start": "76500",
    "end": "82619"
  },
  {
    "text": "finally as I mentioned hopefully some of these lessons can translate to your journey as you evolve your startup",
    "start": "82619",
    "end": "89570"
  },
  {
    "text": "so if you're not familiar with uptake uptake is the leading AI software provider for industrial companies we",
    "start": "89790",
    "end": "98250"
  },
  {
    "text": "were founded a little over four years ago by our CEO and co-founder Brad kewal our president is Ganesh pal",
    "start": "98250",
    "end": "106880"
  },
  {
    "text": "it crashed",
    "start": "115730",
    "end": "118840"
  },
  {
    "text": "it just crashed",
    "start": "121480",
    "end": "124590"
  },
  {
    "text": "[Music] okay as I mentioned we have over a",
    "start": "129740",
    "end": "136950"
  },
  {
    "text": "hundred customers right now across several verticals and I'll go into a couple those verticals here in a moment and we've also been honored along the",
    "start": "136950",
    "end": "144630"
  },
  {
    "text": "way to receive a number of awards we've been named twice to the CNBC disruptor",
    "start": "144630",
    "end": "150270"
  },
  {
    "text": "50 list we've been named to the flat Forbes cloud 100 list we were named by",
    "start": "150270",
    "end": "156870"
  },
  {
    "text": "the World Economic Forum is a technology pioneer and then best of all for us",
    "start": "156870",
    "end": "162000"
  },
  {
    "text": "we're also named one of the best places to work for in Chicago which is great so",
    "start": "162000",
    "end": "168540"
  },
  {
    "text": "in terms of uptake at a glance as I mentioned if I jump into the verticals first here one of those verticals is",
    "start": "168540",
    "end": "175590"
  },
  {
    "text": "rail where we currently provide about four hundred and eighty million dollars in potential value a year monitoring",
    "start": "175590",
    "end": "181890"
  },
  {
    "text": "locomotives in the field so when a locomotive breaks down it's not only expensive to fix that asset itself but",
    "start": "181890",
    "end": "188130"
  },
  {
    "text": "also in terms of the downtime and disruptions of that rail line the wind vertical they're up at the top we",
    "start": "188130",
    "end": "194880"
  },
  {
    "text": "generate about 3.3 million in potential value year per wint park and we do that",
    "start": "194880",
    "end": "200400"
  },
  {
    "text": "predicting things like Maidan bearing failures on wind turbines in terms of",
    "start": "200400",
    "end": "205950"
  },
  {
    "text": "some interesting numbers up at the top there we've already accrued over a 1.2 billion",
    "start": "205950",
    "end": "211950"
  },
  {
    "text": "hours of machine learning data we've done that by monitoring over 200,000",
    "start": "211950",
    "end": "217560"
  },
  {
    "text": "assets in the field the data science side our data scientists are inventors",
    "start": "217560",
    "end": "223530"
  },
  {
    "text": "on over 150 patent applications we have over 1,300 deployed models in production",
    "start": "223530",
    "end": "230490"
  },
  {
    "text": "and it takes us a little under two minutes to deploy a new model into production which is pretty cool",
    "start": "230490",
    "end": "238130"
  },
  {
    "text": "so before I jump into some of these hard problems that I mentioned I want to give a little bit of context so it makes more sense to you at a high level what we do",
    "start": "238760",
    "end": "246410"
  },
  {
    "text": "is something called asset performance management or a p.m. for short and essentially what that means is we",
    "start": "246410",
    "end": "252860"
  },
  {
    "text": "monitor all sorts of assets to make sure not only that they continue to operate but operate efficiently and in order to",
    "start": "252860",
    "end": "259549"
  },
  {
    "text": "do that we lean heavily on our data scientists to build out things like predictive analytics anomaly detection",
    "start": "259549",
    "end": "265810"
  },
  {
    "text": "label correction and then finally we've built a set of applications and AI UX",
    "start": "265810",
    "end": "271010"
  },
  {
    "text": "over the top of that to be able to surface insights that are generated back to our end users end users which is",
    "start": "271010",
    "end": "276650"
  },
  {
    "text": "ultimately what they care about from our platform so in order to power those data",
    "start": "276650",
    "end": "283370"
  },
  {
    "text": "science models we need two categories of data the first is telematics data so this is",
    "start": "283370",
    "end": "288500"
  },
  {
    "text": "high volume high velocity IOT data which is ingested either directly off of sensors on assets themselves or via a",
    "start": "288500",
    "end": "296180"
  },
  {
    "text": "set of intermediary systems and then the second category is something we call contextual data this is additional",
    "start": "296180",
    "end": "303640"
  },
  {
    "text": "important or useful information about the assets we're monitoring themselves things like work order history might be",
    "start": "303640",
    "end": "310010"
  },
  {
    "text": "important and they better inform the data science models that we run and we collect that information from a set of",
    "start": "310010",
    "end": "315680"
  },
  {
    "text": "resource planning customer relationship and content management systems so at a",
    "start": "315680",
    "end": "322550"
  },
  {
    "text": "very high level what we want is information about assets in and generated insights out which sounds",
    "start": "322550",
    "end": "328400"
  },
  {
    "text": "pretty easy which brings me to those hard problems so the first challenge we",
    "start": "328400",
    "end": "333770"
  },
  {
    "text": "ran into is that all data but especially industrial data is very dirty so it",
    "start": "333770",
    "end": "340370"
  },
  {
    "text": "often arrives out of order it's highly volatile we often receive system-wide",
    "start": "340370",
    "end": "346730"
  },
  {
    "text": "snapshots with no deltas comes to us and many predetermined aggregations which",
    "start": "346730",
    "end": "352790"
  },
  {
    "text": "oftentimes don't line up with either the algorithms or the grains that our data science models require and then just in",
    "start": "352790",
    "end": "358850"
  },
  {
    "text": "general it often comes in duplicated partitions coated in all sorts of crazy formats",
    "start": "358850",
    "end": "364160"
  },
  {
    "text": "compressed and to make matters worse industrial data also has passed so a lot",
    "start": "364160",
    "end": "371990"
  },
  {
    "text": "of the systems that we integrate with or very old systems they were designed for other purposes as part of that they are",
    "start": "371990",
    "end": "378560"
  },
  {
    "text": "susceptible to a set of policy changes so we run into things very often where a",
    "start": "378560",
    "end": "383570"
  },
  {
    "text": "customer may have changed the meaning of a time stand from local to UTC time without recording that anywhere they may",
    "start": "383570",
    "end": "389990"
  },
  {
    "text": "have a certain field that they rely on in the context of that fields changed five or six times over the past 20 years",
    "start": "389990",
    "end": "395150"
  },
  {
    "text": "but they want to maintain that context for each of those changes and then",
    "start": "395150",
    "end": "400520"
  },
  {
    "text": "finally most of these integrations do have standards usually that they follow but unfortunately for us it's never the",
    "start": "400520",
    "end": "406670"
  },
  {
    "text": "same standard which kind of defeats the purpose of standards so that's the data",
    "start": "406670",
    "end": "413780"
  },
  {
    "text": "itself in terms of getting the data into our platform that's the second challenge that we have and the main challenge",
    "start": "413780",
    "end": "420080"
  },
  {
    "text": "there is just the sheer number of systems that we need to integrate with not only the systems themselves but also",
    "start": "420080",
    "end": "425960"
  },
  {
    "text": "the permutations of various versions of those systems so ideally those systems",
    "start": "425960",
    "end": "431720"
  },
  {
    "text": "have clean REST API so we can interact with many times they unfortunately don't which means that we need to do more",
    "start": "431720",
    "end": "438500"
  },
  {
    "text": "direct integrations for things like brokers like empty MQTT brokers for example or directly against databases",
    "start": "438500",
    "end": "447260"
  },
  {
    "text": "themselves ideally they're they have things like change data capture systems that we can work with but in the worst",
    "start": "447260",
    "end": "453680"
  },
  {
    "text": "case it looks like scheduled batch oriented direct JDBC calls which is not",
    "start": "453680",
    "end": "459290"
  },
  {
    "text": "a fun place to be",
    "start": "459290",
    "end": "462220"
  },
  {
    "text": "we also have a set of push-based integrations and these are a little bit better for us you know I have to deal",
    "start": "464590",
    "end": "470050"
  },
  {
    "text": "with some of the networking issues that you have to deal with with pull based systems so you don't have to worry about",
    "start": "470050",
    "end": "475300"
  },
  {
    "text": "things like VPN tunnels or firewall rules getting in the way ideally we get information directly off",
    "start": "475300",
    "end": "481150"
  },
  {
    "text": "of those sensors on the assets themselves but in many cases we get file",
    "start": "481150",
    "end": "487480"
  },
  {
    "text": "uploads or drops of CSV files zip files and they may come to us and daily weekly",
    "start": "487480",
    "end": "493300"
  },
  {
    "text": "monthly roll ups where again we're still stuck with either alt or eto batch",
    "start": "493300",
    "end": "498670"
  },
  {
    "text": "processes on our side that we need to maintain still fairly complex once the",
    "start": "498670",
    "end": "506290"
  },
  {
    "text": "data is in our system data volume and velocities or the next fun problem that we encounter so if you look at the slide",
    "start": "506290",
    "end": "513219"
  },
  {
    "text": "here and imagine that each row is the sensor emitting readings and let's say",
    "start": "513220",
    "end": "518860"
  },
  {
    "text": "that each sensor produces 150,000 readings in second that by itself is not",
    "start": "518860",
    "end": "524770"
  },
  {
    "text": "all that challenging but in reality it's not really three sensors it's more in the order of thousands if you multiply",
    "start": "524770",
    "end": "532600"
  },
  {
    "text": "that by tens or thousands of assets that you're monitoring times hundreds or thousands of tenants each with multiple",
    "start": "532600",
    "end": "538900"
  },
  {
    "text": "different data integration paths and associated data flows we found that that compounds pretty quickly and it looks",
    "start": "538900",
    "end": "548350"
  },
  {
    "text": "great on PowerPoint but in reality it actually looks more like this in practice so data often comes in out of",
    "start": "548350",
    "end": "554380"
  },
  {
    "text": "order it might be bursty so for that think of an example of say a mining",
    "start": "554380",
    "end": "559720"
  },
  {
    "text": "truck it goes down into a mine all day it's buffering that telematic data for a number of hours then comes back out of",
    "start": "559720",
    "end": "566830"
  },
  {
    "text": "the mine reconnects back to the network and then you get a sort of a burst or an upload of all of those readings for the",
    "start": "566830",
    "end": "572500"
  },
  {
    "text": "day data may come to us incomplete or worse invalid so think they're of a sort",
    "start": "572500",
    "end": "579880"
  },
  {
    "text": "of a poison pill scenario so you might have a value that you receive and it's a double today and it's a double tomorrow",
    "start": "579880",
    "end": "585310"
  },
  {
    "text": "and then every couple days it comes in as a string or some other unexpected type so your system that you build needs",
    "start": "585310",
    "end": "592030"
  },
  {
    "text": "to be resilient to those sort of anomalous behaviors and then in",
    "start": "592030",
    "end": "597160"
  },
  {
    "text": "addition to that data might come in duplicate it depending on your message guarantees of your underlying platform due to transient issues with a never",
    "start": "597160",
    "end": "604660"
  },
  {
    "text": "connectivity for example or it just might be missing completely and there",
    "start": "604660",
    "end": "610300"
  },
  {
    "text": "are various mitigating steps you can take to work around all of these issues but something we found like anything in",
    "start": "610300",
    "end": "617020"
  },
  {
    "text": "computer science that really comes down to the set of trade-offs you're willing to make within your platform so if I",
    "start": "617020",
    "end": "625990"
  },
  {
    "text": "step back up here for a minute I've talked through data ingestion there on the left-hand side veranda and flow",
    "start": "625990",
    "end": "632740"
  },
  {
    "text": "other capabilities that we require toward the bottom there we need a set of",
    "start": "632740",
    "end": "638140"
  },
  {
    "text": "batch capabilities so these are things like data exploration so that our data scientists can make sense of the data",
    "start": "638140",
    "end": "644620"
  },
  {
    "text": "that's come in in addition to things like training of the models themselves and then just generic batch platform",
    "start": "644620",
    "end": "652089"
  },
  {
    "text": "capabilities like scheduling resource management things like quotas throttling",
    "start": "652089",
    "end": "658350"
  },
  {
    "text": "thanks of that nature and audit history of runs at the top there we also have a",
    "start": "658350",
    "end": "664420"
  },
  {
    "text": "set of streaming capabilities that Roo require this is for being able to apply things like validation transformations",
    "start": "664420",
    "end": "671950"
  },
  {
    "text": "or normalization of the data as it comes in streaming rules for things like outlier detection and then scoring of",
    "start": "671950",
    "end": "679180"
  },
  {
    "text": "the models themselves and then as I mentioned the ultimate goal of the platform is to generate insights back to",
    "start": "679180",
    "end": "685630"
  },
  {
    "text": "our end users so in the upper right here we also have a set of application building capabilities to be able to",
    "start": "685630",
    "end": "691300"
  },
  {
    "text": "quickly configure apps to be able to service those insights back to our end users then I also have some additional",
    "start": "691300",
    "end": "696459"
  },
  {
    "text": "capabilities called out here that I'll come back to you or in a moment",
    "start": "696459",
    "end": "701790"
  },
  {
    "text": "so we decided to build this system and then everybody celebrated and high-five we did it and then as our second and our",
    "start": "701790",
    "end": "709320"
  },
  {
    "text": "third or fourth use case came along we just applied that same pattern sort of in cookie cutter fashion over and over",
    "start": "709320",
    "end": "716040"
  },
  {
    "text": "and over and leveraging the horsepower of AWS behind us it actually made that process pretty straightforward and",
    "start": "716040",
    "end": "721620"
  },
  {
    "text": "pretty easy but one thing we found is over time the more you do that the",
    "start": "721620",
    "end": "727400"
  },
  {
    "text": "consequence of that is that it becomes harder and harder to maintain that consistency across all of those",
    "start": "727400",
    "end": "733740"
  },
  {
    "text": "individual instances and inevitably at some point variance starts to creep into your system so for us at some point we",
    "start": "733740",
    "end": "742830"
  },
  {
    "text": "step back and we change our mindset and our approach a little bit and moved away from that pattern of just repeating the",
    "start": "742830",
    "end": "749400"
  },
  {
    "text": "same thing over and over to more of a platform mindset where we focused less",
    "start": "749400",
    "end": "755070"
  },
  {
    "text": "on solving the immediate need and more in terms of reusable capabilities one",
    "start": "755070",
    "end": "762510"
  },
  {
    "text": "thing you'll find is that's actually not that uncommon of a path for startups to take so you partner with your first",
    "start": "762510",
    "end": "768150"
  },
  {
    "text": "client you build out exactly what they need you're delivering business value and you can actually get pretty far",
    "start": "768150",
    "end": "773880"
  },
  {
    "text": "doing that over and over but at some scale it becomes cost prohibitive to keep doing that so you start to evolve",
    "start": "773880",
    "end": "780450"
  },
  {
    "text": "where for us that looks like a few things you start to move away from sort",
    "start": "780450",
    "end": "786030"
  },
  {
    "text": "of one-off snowflake or bespoke implementations and more towards reusable or generic self-service",
    "start": "786030",
    "end": "791490"
  },
  {
    "text": "capabilities from an organizational or process standpoint you start to think of",
    "start": "791490",
    "end": "797220"
  },
  {
    "text": "things less in terms of stories and team backlogs and more in terms of self-service capabilities so the key",
    "start": "797220",
    "end": "803160"
  },
  {
    "text": "point here is you really want to enable your users to leverage the platform to do the job they need to do without",
    "start": "803160",
    "end": "808710"
  },
  {
    "text": "requiring them to interface with an engineering team the then takes two or three Sprint's to actually make that real and if you could begin to do this",
    "start": "808710",
    "end": "816390"
  },
  {
    "text": "you start to achieve some economy of scale as well as you start to drive down your total cost of ownership",
    "start": "816390",
    "end": "822570"
  },
  {
    "text": "not just from a hosting perspective but also from an organizational overhead",
    "start": "822570",
    "end": "827790"
  },
  {
    "text": "perspective as well and as you do this everyone's use-cases",
    "start": "827790",
    "end": "833680"
  },
  {
    "text": "will be a little bit different but for us that fell into a number of buckets here as I mentioned on the data",
    "start": "833680",
    "end": "838990"
  },
  {
    "text": "ingestion side we started to identify our most common data sources data integration patterns pull those into",
    "start": "838990",
    "end": "844779"
  },
  {
    "text": "reusable connectors and then built out a set of repeatable capabilities to enable",
    "start": "844779",
    "end": "851230"
  },
  {
    "text": "us to easily configure and deploy and monitor those connectors over time without the end-user having to deal with",
    "start": "851230",
    "end": "856779"
  },
  {
    "text": "that each time we also built out what we call data catalog and management",
    "start": "856779",
    "end": "861790"
  },
  {
    "text": "capabilities these are things like being able to define new objects within your system being able to evolve schemas over",
    "start": "861790",
    "end": "868300"
  },
  {
    "text": "time and then having the backing automation in place to be able to automatically apply those configuration",
    "start": "868300",
    "end": "873790"
  },
  {
    "text": "changes to the underlying data stores and data flows the power the platform on the stream processing side the main goal",
    "start": "873790",
    "end": "880389"
  },
  {
    "text": "for us here was to be able to enable data scientists create new data flows generate new data sets without having to",
    "start": "880389",
    "end": "886870"
  },
  {
    "text": "require them to interface with engineering teams each time and not have to be experts and all the stream",
    "start": "886870",
    "end": "893050"
  },
  {
    "text": "processing fundamentals that are required to make this real things like water marketing checkpointing",
    "start": "893050",
    "end": "898209"
  },
  {
    "text": "partitioning of data they don't they no longer have to know all of that just to get their job accomplished the batch",
    "start": "898209",
    "end": "905079"
  },
  {
    "text": "processing side our main goal for this was to provide a clean standardized data",
    "start": "905079",
    "end": "911410"
  },
  {
    "text": "access pattern for a data scientist so regardless of where the data came from what data format it might have come into",
    "start": "911410",
    "end": "918370"
  },
  {
    "text": "the system in they have a repeatable pattern for querying that data and then layering and things like application of",
    "start": "918370",
    "end": "924910"
  },
  {
    "text": "authorization policies on top of that so again it's one less thing for them to worry about and then lastly for a",
    "start": "924910",
    "end": "931480"
  },
  {
    "text": "platform to be real you need some level of operational tooling in place so for us this is its rotation of all of our",
    "start": "931480",
    "end": "938050"
  },
  {
    "text": "services all of our data flows or connectors and are backing infrastructure to give you the",
    "start": "938050",
    "end": "943600"
  },
  {
    "text": "observability into your system so that you're able to face some of the challenges and scalability concerns as I",
    "start": "943600",
    "end": "949029"
  },
  {
    "text": "mentioned so we built all of this with the ultimate goal of providing a platform",
    "start": "949029",
    "end": "955380"
  },
  {
    "text": "for a data scientist to have a seamless way of onboarding data within to the",
    "start": "955380",
    "end": "960450"
  },
  {
    "text": "system in a simple efficient repeatable pattern and we did this for a couple",
    "start": "960450",
    "end": "967170"
  },
  {
    "text": "reasons that I'll give it over to Dan for to talk through as part of our facts of life",
    "start": "967170",
    "end": "973400"
  },
  {
    "text": "so thanks CJ for running through kind of the problems we solve in our evolution",
    "start": "975200",
    "end": "980640"
  },
  {
    "text": "as a company there's one other piece that I want to kind of dive into and it's facts of life when it comes to",
    "start": "980640",
    "end": "986880"
  },
  {
    "text": "machine learning so in 2014",
    "start": "986880",
    "end": "992520"
  },
  {
    "text": "several researchers at Google published a paper and they basically say machine learning is the high interest credit",
    "start": "992520",
    "end": "998250"
  },
  {
    "text": "card of technical debt and this is not because the machine learning code is hard to learn or it's difficult to kind",
    "start": "998250",
    "end": "1005810"
  },
  {
    "text": "of reason about it's mostly because of all the supporting services and everything that you need to get up and",
    "start": "1005810",
    "end": "1010880"
  },
  {
    "text": "running and also have repeatable so like CJ was mentioning data ingestion flows",
    "start": "1010880",
    "end": "1017290"
  },
  {
    "text": "data validation remediation those things have to be consistent in training as well as in your runtime for scoring so",
    "start": "1017290",
    "end": "1025819"
  },
  {
    "text": "to kind of call this out with a graphic it kind of looks like this the green box",
    "start": "1025820",
    "end": "1031310"
  },
  {
    "text": "in the middle we have what people talk about so this is what everybody says AI and dust really I but really the hard",
    "start": "1031310",
    "end": "1039050"
  },
  {
    "text": "parts from a data engineering perspective are all the blue boxes that we have around here so only a small",
    "start": "1039050",
    "end": "1045380"
  },
  {
    "text": "fraction of the real world ml systems are really focused on solving the green",
    "start": "1045380",
    "end": "1051080"
  },
  {
    "text": "box they have to take care of all this other stuff around it and everything is",
    "start": "1051080",
    "end": "1057470"
  },
  {
    "text": "hard so these are difficult problems to solve as you go because in data science",
    "start": "1057470",
    "end": "1064340"
  },
  {
    "text": "changing anything changes everything and this is a axiom that I've learned upon",
    "start": "1064340",
    "end": "1071090"
  },
  {
    "text": "starting at uptake you have to have things that are repeatable but not just repeatable you have to have the same",
    "start": "1071090",
    "end": "1077240"
  },
  {
    "text": "validation in place for training otherwise the models are out there they're running they're scoring things and",
    "start": "1077240",
    "end": "1083660"
  },
  {
    "text": "may not detect that there's actually like false positives or it's not detecting something because your",
    "start": "1083660",
    "end": "1089540"
  },
  {
    "text": "remediation process changed or data validation change or the way the data arrived and how its clustered changed so",
    "start": "1089540",
    "end": "1095420"
  },
  {
    "text": "that training context doesn't know so you have to keep this in mind so as you build the data verification ingestion",
    "start": "1095420",
    "end": "1101540"
  },
  {
    "text": "etc and the tools to monitor that you have to be aware of all of those things",
    "start": "1101540",
    "end": "1106790"
  },
  {
    "text": "impacting data science that does scoring because ultimately the only thing you care about is getting your insights out",
    "start": "1106790",
    "end": "1113000"
  },
  {
    "text": "and actual outcomes from that so just to recap this small extra",
    "start": "1113000",
    "end": "1119390"
  },
  {
    "text": "flavoring I kind of put an xkcd up here you know the it's a pile of linear",
    "start": "1119390",
    "end": "1125270"
  },
  {
    "text": "algebra and we just mix it until we get the right output but really it's we take",
    "start": "1125270",
    "end": "1130790"
  },
  {
    "text": "this data that's super dirty from the source systems and we scale it up to",
    "start": "1130790",
    "end": "1136750"
  },
  {
    "text": "150,000 writes per sensor with an asset having you know thousands of sensors",
    "start": "1136750",
    "end": "1142940"
  },
  {
    "text": "hundreds of thousands of sensors or us aggregating those across a tenant and then you spin up data science models on",
    "start": "1142940",
    "end": "1148790"
  },
  {
    "text": "top of it after you do training so what could go wrong right in this whole process",
    "start": "1148790",
    "end": "1156100"
  },
  {
    "text": "so as a start-up we've done this process over time and CJ kind of shared our",
    "start": "1156820",
    "end": "1162760"
  },
  {
    "text": "evolution of platform a little bit but I'm going to talk about continuous evolution because I think it's so key to growing so there's four points that I",
    "start": "1162760",
    "end": "1173950"
  },
  {
    "text": "really want to dive into you hear really it's number one is proof of concept",
    "start": "1173950",
    "end": "1179200"
  },
  {
    "text": "number two is building things out number three is learning from those things and kind of reincorporating on and four is",
    "start": "1179200",
    "end": "1186210"
  },
  {
    "text": "automating and making that process as repeat a low as possible so for proof of",
    "start": "1186210",
    "end": "1193180"
  },
  {
    "text": "concept this is really like getting from works on my machine to actually working",
    "start": "1193180",
    "end": "1199870"
  },
  {
    "text": "the cloud and this is where like AWS really allows you to go all-in as soon as you're ready to start so you want to",
    "start": "1199870",
    "end": "1206980"
  },
  {
    "text": "create real-world data science models and real world data sets and in order to",
    "start": "1206980",
    "end": "1213160"
  },
  {
    "text": "do that you need to take some subset of that and get it quickly spun up so you can experiment and to play around this",
    "start": "1213160",
    "end": "1218320"
  },
  {
    "text": "is where AWS will let you spin up any type of resource super quickly or you can use like the managed services like",
    "start": "1218320",
    "end": "1224920"
  },
  {
    "text": "sage maker you could choose to do the beefiest boxes or lean into GPU based programming but a w hat AWS has all of",
    "start": "1224920",
    "end": "1233320"
  },
  {
    "text": "these things ready for you to do a proof of concept and the goal here is really take your idea and and prove it out just",
    "start": "1233320",
    "end": "1239740"
  },
  {
    "text": "make sure that it actually works the way that you expect or that you can say that it's valid once you have that all set up",
    "start": "1239740",
    "end": "1249100"
  },
  {
    "text": "this is really where you go next so this is scaling out so when you think about",
    "start": "1249100",
    "end": "1254890"
  },
  {
    "text": "this and proof of concept phase everything's on the table you have but you don't really have to make mini trade-offs this is where you're saying I",
    "start": "1254890",
    "end": "1261970"
  },
  {
    "text": "have a specific use case for data ingestion and I need to account for real world data sets on distributed systems",
    "start": "1261970",
    "end": "1268120"
  },
  {
    "text": "so all the complexity that you kind of like ignore in the first part comes in here and this is where like manage",
    "start": "1268120",
    "end": "1274900"
  },
  {
    "text": "services or elastic scaling can drastically reduce the time to go from like that proofs that prove a concept",
    "start": "1274900",
    "end": "1280510"
  },
  {
    "text": "into actual production code it's it's very easy if you are choosing good abstractions which AWS managed",
    "start": "1280510",
    "end": "1287510"
  },
  {
    "text": "services have a ton of to kind of lean in and scale up and out without having",
    "start": "1287510",
    "end": "1293030"
  },
  {
    "text": "to do much work on urine so really like using the infrastructure as a service and you might start with something",
    "start": "1293030",
    "end": "1299150"
  },
  {
    "text": "that's not custom at all it's just like out-of-the-box Postgres running on RDS and then as you grow you might find yet",
    "start": "1299150",
    "end": "1304790"
  },
  {
    "text": "you have to tweak that or you're doing sharding or something else custom you can layer that on top or look at other offerings they have so if I come back",
    "start": "1304790",
    "end": "1313910"
  },
  {
    "text": "here to the hard parts AWS checks the",
    "start": "1313910",
    "end": "1319490"
  },
  {
    "text": "box across the board whether it's data collection process management monitoring",
    "start": "1319490",
    "end": "1325660"
  },
  {
    "text": "orchestration across the surveying infrastructure all of those things are",
    "start": "1325660",
    "end": "1331190"
  },
  {
    "text": "there even some of the more like things that are based around ml or out-of-the-box ml are now coming online",
    "start": "1331190",
    "end": "1337550"
  },
  {
    "text": "so you can see that if you're using the AWS stuff you can quickly get up to",
    "start": "1337550",
    "end": "1344210"
  },
  {
    "text": "speed and kind of out to production so the last or the third step here is",
    "start": "1344210",
    "end": "1352090"
  },
  {
    "text": "repeatability so you do all this stuff you get things up and running but before",
    "start": "1352090",
    "end": "1357260"
  },
  {
    "text": "you can go do more proof of concepts and start running you want to kind of take the patterns and distill out of the work",
    "start": "1357260",
    "end": "1363140"
  },
  {
    "text": "that you did what the trade-offs and what architectural decisions you made were at this point you kind of go from",
    "start": "1363140",
    "end": "1370100"
  },
  {
    "text": "saying instead of this bespoke kind of integration I want to say okay here's the infrastructure as code bit that got",
    "start": "1370100",
    "end": "1376910"
  },
  {
    "text": "this up and running here's how I think about scalability is it like up or out here's I'm looking at compute IO",
    "start": "1376910",
    "end": "1383660"
  },
  {
    "text": "parallelism offline processing but in in doing that you kind of distill these",
    "start": "1383660",
    "end": "1390170"
  },
  {
    "text": "things out as standards and then the next time around you have that context and you can learn from it so because",
    "start": "1390170",
    "end": "1396440"
  },
  {
    "text": "there are such a huge array of services there there's learning baked in at the infrastructure level already with many",
    "start": "1396440",
    "end": "1402320"
  },
  {
    "text": "of the AWS AWS offerings and this is just kind of a call out to when you're",
    "start": "1402320",
    "end": "1407480"
  },
  {
    "text": "iterating definitely pull those things out from an architectural perspective so you can continue you do",
    "start": "1407480",
    "end": "1412600"
  },
  {
    "text": "to do that yourself so the last thing I",
    "start": "1412600",
    "end": "1418750"
  },
  {
    "text": "kind of want to throw out here is layman's law of software evolution and I think this is as true as when it was",
    "start": "1418750",
    "end": "1425770"
  },
  {
    "text": "originally written and it kind of says a program that is used and that as an implementation of its specification",
    "start": "1425770",
    "end": "1431890"
  },
  {
    "text": "reflects some other reality undergoes continual change or it becomes progressively less useful seems pretty",
    "start": "1431890",
    "end": "1439510"
  },
  {
    "text": "obvious but the the point here is change is going to be constant as you're",
    "start": "1439510",
    "end": "1444700"
  },
  {
    "text": "building things and the things that you roll out initially from like a proof of concept should always be kind of as you",
    "start": "1444700",
    "end": "1451510"
  },
  {
    "text": "go to production with those you're thinking about how can I continue to look at new contexts new services that are offered new maybe you're you're",
    "start": "1451510",
    "end": "1458320"
  },
  {
    "text": "entering a new type of integration a new type of technology and you come back to this question of you know do I continue",
    "start": "1458320",
    "end": "1466360"
  },
  {
    "text": "to invest in what I have or am I going to kind of build it again because otherwise if I don't do anything I'm",
    "start": "1466360",
    "end": "1472150"
  },
  {
    "text": "going to have that system atrophy and end up building again even if I don't want to so from here we're gonna kind of",
    "start": "1472150",
    "end": "1482350"
  },
  {
    "text": "get into summarization I'm gonna hand it over to Brad boven he's going to talk to you about data engineering the startup",
    "start": "1482350",
    "end": "1488170"
  },
  {
    "text": "way and platforming so thank you you",
    "start": "1488170",
    "end": "1494290"
  },
  {
    "text": "guys hear me okay I have a different mic than they do so I'll try to speak up so",
    "start": "1494290",
    "end": "1499720"
  },
  {
    "text": "thank you very much to Dan and CJ as I stood off to the side awkwardly they were talking to you about a lot of the",
    "start": "1499720",
    "end": "1505210"
  },
  {
    "text": "things that I'm going to kind of use that context in order to stand on my soapbox a little bit and talk about the",
    "start": "1505210",
    "end": "1511210"
  },
  {
    "text": "principles that have got us to where we are from a start-up pull from a data engineering perspective and talking a lot about platforms and how we think",
    "start": "1511210",
    "end": "1517240"
  },
  {
    "text": "about them I'll definitely say that we've evolved to get to this mindset you don't necessarily start with this but I",
    "start": "1517240",
    "end": "1523810"
  },
  {
    "text": "think the principles and the tenants that I'm going to talk about hopefully it will help you inform the way that you'll go about it going forward so",
    "start": "1523810",
    "end": "1533010"
  },
  {
    "text": "how do we start we're talking about platforms we're talking about data engineering how did we actually start",
    "start": "1533010",
    "end": "1538440"
  },
  {
    "text": "our platform it wasn't like it is today we'll talk at the end more about what our platform looks like today but at",
    "start": "1538440",
    "end": "1545250"
  },
  {
    "text": "first it was a monolith it was a group of prototypes kind of smashed together it was tested locally deployed on Prem",
    "start": "1545250",
    "end": "1552750"
  },
  {
    "text": "and then scaled out through AWS you know we kept from there we kept building and",
    "start": "1552750",
    "end": "1558750"
  },
  {
    "text": "iterating and proving that uptake could predict the future we use our data science and our platform and our",
    "start": "1558750",
    "end": "1564780"
  },
  {
    "text": "engineering to be able to predict when assets are going to fail so with our",
    "start": "1564780",
    "end": "1569790"
  },
  {
    "text": "technology and with our data science built-in we're predicting asset failures before they happen which allows our",
    "start": "1569790",
    "end": "1575250"
  },
  {
    "text": "customers to be more productive more reliable more safe and more secure so",
    "start": "1575250",
    "end": "1580260"
  },
  {
    "text": "from there as we started to scale and grow we moved more into a microservices architecture which allowed us to",
    "start": "1580260",
    "end": "1585870"
  },
  {
    "text": "decouple our teams and you know really increase the speed of our experimentation allow teams to have",
    "start": "1585870",
    "end": "1592560"
  },
  {
    "text": "better ownership over their services and control their operations and own their",
    "start": "1592560",
    "end": "1597810"
  },
  {
    "text": "code better than they were before so this allows you to create those independent life cycles that happen kind",
    "start": "1597810",
    "end": "1603900"
  },
  {
    "text": "of team by team as part of this journey AWS really allows you to be flexible and",
    "start": "1603900",
    "end": "1611880"
  },
  {
    "text": "use as much of it as you want at different times going from being able to take fully managed services which we'll",
    "start": "1611880",
    "end": "1617580"
  },
  {
    "text": "talk about quite a bit all the way to we have you know bare-bones ec2 instances which you can customize and do whatever",
    "start": "1617580",
    "end": "1623460"
  },
  {
    "text": "you want with so as we go through this journey then both Dan and CJ talked",
    "start": "1623460",
    "end": "1629340"
  },
  {
    "text": "about this quite a bit iteration is key here you're trying to survive you're trying to figure out what's the next thing that's going to",
    "start": "1629340",
    "end": "1635430"
  },
  {
    "text": "land you the next big client how what's the next feature that you need to get out just iterate iterate and evolve and",
    "start": "1635430",
    "end": "1641040"
  },
  {
    "text": "figure out the decisions that you have to make in order to get there all right so data engineering the startup way",
    "start": "1641040",
    "end": "1648710"
  },
  {
    "text": "there's about five different things that I'm going to focus on and talk about and so we'll go into each one of these and a",
    "start": "1648710",
    "end": "1654750"
  },
  {
    "text": "little bit more detail so first focusing on value",
    "start": "1654750",
    "end": "1660560"
  },
  {
    "text": "leverage AWS focus on the things that matter to you and your business simplify",
    "start": "1660560",
    "end": "1667140"
  },
  {
    "text": "the problem set that you have don't solve problems that you don't have don't create problems for yourself that you don't have know what it is you're",
    "start": "1667140",
    "end": "1673560"
  },
  {
    "text": "building and focus on those things and those things only you can create problems and like focus on edge cases",
    "start": "1673560",
    "end": "1679590"
  },
  {
    "text": "and all that type of stuff focus in on what's really important and offload the rest of it to services like",
    "start": "1679590",
    "end": "1684840"
  },
  {
    "text": "AWS that can allow you to leverage those manage services to go further faster",
    "start": "1684840",
    "end": "1690950"
  },
  {
    "text": "make trade-offs force them know what those trade-offs are understand why",
    "start": "1690950",
    "end": "1696090"
  },
  {
    "text": "you're making them but make them they're really good for what you're trying to do early on next focus in on a specific",
    "start": "1696090",
    "end": "1703500"
  },
  {
    "text": "problem set there's you know building a platform that's generic and can do a lot of things you don't start there you",
    "start": "1703500",
    "end": "1709980"
  },
  {
    "text": "start with laser focus on what it is that you want to build and why you want to build it and having everybody on your",
    "start": "1709980",
    "end": "1715170"
  },
  {
    "text": "team know why that's important so make sure that that's fundamental and the way that you approach this finally focus on",
    "start": "1715170",
    "end": "1722430"
  },
  {
    "text": "again what's critical path in doing so by partner leverage things like AWS",
    "start": "1722430",
    "end": "1727890"
  },
  {
    "text": "leverage open source figure out the things that can make you go faster without you having to spend the time to",
    "start": "1727890",
    "end": "1733050"
  },
  {
    "text": "maintain and build and ultimately own those services out in production figure",
    "start": "1733050",
    "end": "1738870"
  },
  {
    "text": "out the ways that you can offload that responsibility to someone like AWS next",
    "start": "1738870",
    "end": "1744840"
  },
  {
    "text": "choose good abstractions so abstractions over different managed services like AWS",
    "start": "1744840",
    "end": "1751890"
  },
  {
    "text": "allow you to iterate in scale and simplify your deployment cycles so that's going to give you more",
    "start": "1751890",
    "end": "1757950"
  },
  {
    "text": "flexibility because things are just going to change things should always be changing and you need to embrace the",
    "start": "1757950",
    "end": "1763080"
  },
  {
    "text": "change because it's going to keep happening ultimately the code that you're running right now you should",
    "start": "1763080",
    "end": "1768150"
  },
  {
    "text": "aspire to not running that code 12 months from now in production or maybe even sooner than that so embrace the",
    "start": "1768150",
    "end": "1773580"
  },
  {
    "text": "change understand that's going to keep happening and create abstractions over that to minimize the impact that you have upstream in your sac",
    "start": "1773580",
    "end": "1781490"
  },
  {
    "text": "all right act like an enterprise this one is super super simple so when you",
    "start": "1782429",
    "end": "1788350"
  },
  {
    "text": "use world class Global Services you get the service levels of world class global services so use them they can be the",
    "start": "1788350",
    "end": "1795159"
  },
  {
    "text": "backbone for the security and stability that you need is a business to turn a two-person team or a small team into an",
    "start": "1795159",
    "end": "1801850"
  },
  {
    "text": "army of people that feels like you've handled a lot of the hard problems that you could spend time and money on people",
    "start": "1801850",
    "end": "1808450"
  },
  {
    "text": "developing and building for things that you don't need to leverage the enterprise class capabilities that you",
    "start": "1808450",
    "end": "1814360"
  },
  {
    "text": "get with something like Amazon that allows you to create and move very",
    "start": "1814360",
    "end": "1819789"
  },
  {
    "text": "quickly and scale your business very fast next invest invest in technology",
    "start": "1819789",
    "end": "1827200"
  },
  {
    "text": "and invest in people so from the perspective of technology lean into platform and leading to platform early",
    "start": "1827200",
    "end": "1833950"
  },
  {
    "text": "it's really important to have that mindset early on it's gonna change in the platform that you have today is it",
    "start": "1833950",
    "end": "1839169"
  },
  {
    "text": "going to be the platform that you have years from now but having that mindset going in is going to change and alter the decision-making process that you",
    "start": "1839169",
    "end": "1845289"
  },
  {
    "text": "have and you're going to be better off for it from a people perspective invest in your teams invest in your people",
    "start": "1845289",
    "end": "1850720"
  },
  {
    "text": "invest in your culture we're gonna talk more a little bit about culture and uptake and how we do it in just a few minutes but that's super super important",
    "start": "1850720",
    "end": "1857529"
  },
  {
    "text": "to building teams that are highly productive when it comes to platform and",
    "start": "1857529",
    "end": "1863470"
  },
  {
    "text": "leading in their think about things like what are the important paved roads things like AWS as best practices",
    "start": "1863470",
    "end": "1869700"
  },
  {
    "text": "Netflix pave Road philosophy they're real and they work and they're awesome so read about them understand what are",
    "start": "1869700",
    "end": "1875919"
  },
  {
    "text": "the paved roads for your particular business and make sure that you're on them and creating creating those paved",
    "start": "1875919",
    "end": "1881320"
  },
  {
    "text": "roads for people on your team alright next be open there's a lot of incredibly",
    "start": "1881320",
    "end": "1889809"
  },
  {
    "text": "smart and awesome people working in the open sources open source community solving projects that have a ton of",
    "start": "1889809",
    "end": "1895929"
  },
  {
    "text": "value for things that you're doing right now so leverage that open source software contribute to it and give back figure",
    "start": "1895929",
    "end": "1903580"
  },
  {
    "text": "out how you do it at uptake we both leverage a lot of open source in our stack and we also have open source you",
    "start": "1903580",
    "end": "1910179"
  },
  {
    "text": "can find us on github uptake open source we've got of Awesome projects there and we love to have any number of us contributors then",
    "start": "1910179",
    "end": "1919840"
  },
  {
    "text": "finally have fun be flexible adapt to the change that we talked about make",
    "start": "1919840",
    "end": "1925180"
  },
  {
    "text": "decisions quickly so that your team can adapt to them and just find ways to encourage a culture of having fun I",
    "start": "1925180",
    "end": "1931600"
  },
  {
    "text": "would say one of the most important ways to doing that is you know leveraging cool technology is awesome and engineers",
    "start": "1931600",
    "end": "1938410"
  },
  {
    "text": "always want to play with the coolest and newest stuff but actually doing stuff that matters and delivering code into production that's valuable for your",
    "start": "1938410",
    "end": "1944830"
  },
  {
    "text": "users that's delighting your users and getting that feedback back to your engineers is gonna be the best way to get them having",
    "start": "1944830",
    "end": "1951490"
  },
  {
    "text": "fun and get them engaged in what they're doing alright so take it to take a step",
    "start": "1951490",
    "end": "1958990"
  },
  {
    "text": "back we've talked a lot about platform CJ and Dan both kind of walked us through what is uptake how do we think",
    "start": "1958990",
    "end": "1965800"
  },
  {
    "text": "about the world and what are the problems that we're solving we talked about AI and ml platforms in the IOT",
    "start": "1965800",
    "end": "1971770"
  },
  {
    "text": "space we talked about how it's just really hard problems that we're trying to solve to kind of make matters worse",
    "start": "1971770",
    "end": "1979150"
  },
  {
    "text": "so to speak Dan talked about how when you make one change in an AI nml platform you ultimately are impacting",
    "start": "1979150",
    "end": "1985090"
  },
  {
    "text": "everything in the system which just compounds problems that you could have and then I walk through some of the key",
    "start": "1985090",
    "end": "1990700"
  },
  {
    "text": "tenants of data engineering in a start-up sense that allow you to grow and scale your engineering team if you",
    "start": "1990700",
    "end": "1996640"
  },
  {
    "text": "can kind of embody those principles and work with them so now what I want to do is we've talked a lot about platforms",
    "start": "1996640",
    "end": "2002760"
  },
  {
    "text": "what they are why you should use them why you should lean into them and so hopefully most of you are like okay",
    "start": "2002760",
    "end": "2008460"
  },
  {
    "text": "that's great I get it I want to do it so how do I get myself one of those so platform 101 what",
    "start": "2008460",
    "end": "2016320"
  },
  {
    "text": "are the things that are really important when you're thinking about platform and like what are the important principles",
    "start": "2016320",
    "end": "2023070"
  },
  {
    "text": "that you need to be thinking about so first of all the most important thing that I would say is having this mindset",
    "start": "2023070",
    "end": "2029400"
  },
  {
    "text": "and thinking about it definitely is going to alter your trajectory so number one be opinionated I really think that",
    "start": "2029400",
    "end": "2035790"
  },
  {
    "text": "this is the most important aspect of what you can do make the tough calls figure out what you",
    "start": "2035790",
    "end": "2041240"
  },
  {
    "text": "are I think that especially early on knowing the things that you're not actually end up being way more important",
    "start": "2041240",
    "end": "2047450"
  },
  {
    "text": "than the things that you could be or that you're going to be in the future knowing that I'm not doing this allows",
    "start": "2047450",
    "end": "2052520"
  },
  {
    "text": "you to avoid a lot of those specific edge cases where your engineers will kind of get wrapped up around oh well",
    "start": "2052520",
    "end": "2058580"
  },
  {
    "text": "you know I got we might have to solve this or we might need to do that someday if you're very clear about no we're not",
    "start": "2058580",
    "end": "2064310"
  },
  {
    "text": "that and we're not that right now that allows you to simplify a lot of those decisions second is build a platform",
    "start": "2064310",
    "end": "2071240"
  },
  {
    "text": "that allows your team to build software on top of it so frameworks and toolkits",
    "start": "2071240",
    "end": "2076520"
  },
  {
    "text": "that allow you to your team to scale out their systems and build them faster that",
    "start": "2076520",
    "end": "2083388"
  },
  {
    "text": "that's going to be key when it when you think about platforms so what are the ways that you can build tools that allow others to build other services and",
    "start": "2083389",
    "end": "2090200"
  },
  {
    "text": "applications on top of those and not have to completely reinvent the wheel every single time furthermore when you",
    "start": "2090200",
    "end": "2096408"
  },
  {
    "text": "see them reinventing the wheel every time ask the questions of you know what is the opinionated call I can make about",
    "start": "2096409",
    "end": "2102320"
  },
  {
    "text": "how this should work at my company this is the way that we do it here so that everybody is not trying to kind of",
    "start": "2102320",
    "end": "2108500"
  },
  {
    "text": "reinvent the wheel in their own different team by doing that you can say this is how we do it and this is how we",
    "start": "2108500",
    "end": "2114260"
  },
  {
    "text": "want to do it and then allow where it's absolutely necessary some configuration parameters to allow you to kind of say",
    "start": "2114260",
    "end": "2119930"
  },
  {
    "text": "but it's a little bit different here and it's a little bit different here but this is actually how we really think it should be done next we've talked about",
    "start": "2119930",
    "end": "2126980"
  },
  {
    "text": "this quite a bit but change is always going to be happening you need to embrace it you need to understand you need to build good abstractions that",
    "start": "2126980",
    "end": "2133340"
  },
  {
    "text": "insulate yourself from that change as you're building out your platform next",
    "start": "2133340",
    "end": "2139600"
  },
  {
    "text": "this one can be a little bit harder especially early on but separation between your platform and your",
    "start": "2139600",
    "end": "2144859"
  },
  {
    "text": "applications is really going to be important as you go it can become very easy to let those things really come",
    "start": "2144859",
    "end": "2151040"
  },
  {
    "text": "Ingle together and that's gonna force a lot of interesting trade-offs within your engineering team of like okay well",
    "start": "2151040",
    "end": "2157070"
  },
  {
    "text": "it'll be easier to have them become more co-mingled force the separation between them it will pay off in the long run and",
    "start": "2157070",
    "end": "2163340"
  },
  {
    "text": "make sure that that continues to happen all right so you've leaned in the",
    "start": "2163340",
    "end": "2169449"
  },
  {
    "text": "platform you've bought into some of these principles that we've been talking about now I need to start to scale your",
    "start": "2169449",
    "end": "2174880"
  },
  {
    "text": "team so you can go really fast early on with a small close-knit group that's all standing around talking to each other",
    "start": "2174880",
    "end": "2180819"
  },
  {
    "text": "all the time and that's awesome but eventually you're going to need to start to add to your team and grow the team",
    "start": "2180819",
    "end": "2186640"
  },
  {
    "text": "and I'd encourage you to not pay that coherence penalty of adding more people into the group for as long as you can",
    "start": "2186640",
    "end": "2192309"
  },
  {
    "text": "but inevitably you're going to need to so when that happens the most important thing is to create clearly defined",
    "start": "2192309",
    "end": "2198249"
  },
  {
    "text": "service boundaries and contracts between those teams and communicate it out effectively to all those groups so that",
    "start": "2198249",
    "end": "2203680"
  },
  {
    "text": "they know where those boundaries line up there's always going to be complexity",
    "start": "2203680",
    "end": "2209259"
  },
  {
    "text": "and uncertainty so we talked about understanding and making clear opinionated trade-offs that's great the",
    "start": "2209259",
    "end": "2215709"
  },
  {
    "text": "other thing that you really need to make sure that you're doing is identifying the things that will actually kill you those are the things that actually",
    "start": "2215709",
    "end": "2221559"
  },
  {
    "text": "matter make sure you get data about what those things are and make the right decision for all the other decisions I",
    "start": "2221559",
    "end": "2227589"
  },
  {
    "text": "would argue that making the fast decision that is isn't necessarily right is actually going to be the better",
    "start": "2227589",
    "end": "2233859"
  },
  {
    "text": "decision in the long run because it wasn't consensus consensus based and slow next have a have a mission be",
    "start": "2233859",
    "end": "2242949"
  },
  {
    "text": "mission driven have your engineering team know and embody why what they're doing is important and how everything",
    "start": "2242949",
    "end": "2249190"
  },
  {
    "text": "that they're doing contributes to that overall mission every person on your engineering team should be able to go and give your pitch about why what",
    "start": "2249190",
    "end": "2256029"
  },
  {
    "text": "you're building is important that's so important to driving engagement within your team finally fiercely break down",
    "start": "2256029",
    "end": "2263949"
  },
  {
    "text": "walls and silos around different teams both within your group and outside your group so as your team's start to grow",
    "start": "2263949",
    "end": "2269890"
  },
  {
    "text": "it's gonna become natural for oh this is my team and that's your team even within the engineering group break down those",
    "start": "2269890",
    "end": "2275829"
  },
  {
    "text": "walls and barriers and make sure people are really working together and then outside of your engineering team really",
    "start": "2275829",
    "end": "2280930"
  },
  {
    "text": "make sure that there aren't any barriers and silos there everybody should understand and have visibility into what",
    "start": "2280930",
    "end": "2285999"
  },
  {
    "text": "your team is doing and why they're doing it so that everybody is working together",
    "start": "2285999",
    "end": "2290969"
  },
  {
    "text": "so I talked a little bit about culture culture is ultimately going to be the lifeblood of what it is that you're building because as you start to scale",
    "start": "2291650",
    "end": "2299120"
  },
  {
    "text": "and grow it's no longer just you as an engineering leader making the decisions you have to push those decisions down",
    "start": "2299120",
    "end": "2304910"
  },
  {
    "text": "and so you need to empower people on your team to make the right decisions even when nobody is looking so culture",
    "start": "2304910",
    "end": "2312050"
  },
  {
    "text": "is driven by engagement which is driven which ultimately drives execution that's",
    "start": "2312050",
    "end": "2317750"
  },
  {
    "text": "super important so there's a lot of different ways that we drive culture and uptake and there's different inflection",
    "start": "2317750",
    "end": "2323630"
  },
  {
    "text": "points as as a start-up grows from five engineers the culture that you have is very different from 20 engineers to 50",
    "start": "2323630",
    "end": "2330620"
  },
  {
    "text": "engineers and a hundred and those different inflection points you have to ask yourself how can I continue to carry",
    "start": "2330620",
    "end": "2335780"
  },
  {
    "text": "on the culture that I want that embodies the way that I think about the things we need to be building as part of that",
    "start": "2335780",
    "end": "2341990"
  },
  {
    "text": "process you know we do a number of things that uptake like hackathons and",
    "start": "2341990",
    "end": "2347470"
  },
  {
    "text": "engineering talks and a lot of like development opportunities within our teams where we have experts within our",
    "start": "2347470",
    "end": "2353900"
  },
  {
    "text": "teams giving talks and talking about things that they understand really well and bringing in people to talk about",
    "start": "2353900",
    "end": "2359000"
  },
  {
    "text": "things that we want to learn more about all of that stuff is super super important but I would argue that while",
    "start": "2359000",
    "end": "2364610"
  },
  {
    "text": "you definitely want to do that and there's definitely an amount of that thing that you need the most important",
    "start": "2364610",
    "end": "2369860"
  },
  {
    "text": "thing that's going to drive engagement with your team's is like I said before delivering software into production that",
    "start": "2369860",
    "end": "2374990"
  },
  {
    "text": "your team's understand how they fit in they understand the vision and why it's important and you're getting that feedback loop back to them to say my",
    "start": "2374990",
    "end": "2382070"
  },
  {
    "text": "thing is important because they hadn't had an impact on my customers bottom line or it changed the way that they",
    "start": "2382070",
    "end": "2387710"
  },
  {
    "text": "worked okay so we've taken a journey of data",
    "start": "2387710",
    "end": "2394190"
  },
  {
    "text": "engineering at a start-up we've talked a lot about platforms scaling and building out your team so let's talk a little bit",
    "start": "2394190",
    "end": "2401240"
  },
  {
    "text": "about uptakes portfolio of our platform our applications and the services that we offer so ad uptake I'll talk about",
    "start": "2401240",
    "end": "2409100"
  },
  {
    "text": "the specific incarnation of the platform that we have today and the way that it looks like today based on the way that",
    "start": "2409100",
    "end": "2414950"
  },
  {
    "text": "it's been evolved from the what CJ and Dan both talked about kind of embodying the principles that I've been discussing",
    "start": "2414950",
    "end": "2420320"
  },
  {
    "text": "but one of the key things that we build on top of that platform is our applications so our products are",
    "start": "2420320",
    "end": "2427599"
  },
  {
    "text": "focused on KPIs and outcomes that deliver financial outcomes to clients",
    "start": "2427599",
    "end": "2433849"
  },
  {
    "text": "within industry uptakes DNA is all about industry and that's at the heart of everything that we do so our",
    "start": "2433849",
    "end": "2440200"
  },
  {
    "text": "applications are delivered software-as-a-service that target specific KPIs within our customers",
    "start": "2440200",
    "end": "2445490"
  },
  {
    "text": "businesses that we're trying to affect and move in the right direction our services offerings are comprehensive and",
    "start": "2445490",
    "end": "2452660"
  },
  {
    "text": "that we take both our platform and our products and applications built on top of that platform and customize them to",
    "start": "2452660",
    "end": "2458119"
  },
  {
    "text": "meet you wherever you're at on your digital transformation journey all right so",
    "start": "2458119",
    "end": "2464810"
  },
  {
    "text": "we've talked a lot about the platform the uptake platform today is something",
    "start": "2464810",
    "end": "2470089"
  },
  {
    "text": "that we've built from the ground up so we got a lot of insight from both CJ and Dan on exactly how we've done that one",
    "start": "2470089",
    "end": "2476089"
  },
  {
    "text": "of the things that I think is most important is this idea of an AI first platform a lot of the other people in",
    "start": "2476089",
    "end": "2482359"
  },
  {
    "text": "this space they have kind of bolted on AI over time which is not something that we've done we've thought about AI from",
    "start": "2482359",
    "end": "2488720"
  },
  {
    "text": "the very beginning as Dan was saying a change in an AI and m/l platform affects",
    "start": "2488720",
    "end": "2493820"
  },
  {
    "text": "everything else in that system so you have to think about it going in and if you do it as an afterthought that's",
    "start": "2493820",
    "end": "2498920"
  },
  {
    "text": "going to create a lot of some optimal results within the platform and the applications that you build on top of",
    "start": "2498920",
    "end": "2504050"
  },
  {
    "text": "them so our platform is fully managed and what that means is that you have you",
    "start": "2504050",
    "end": "2509570"
  },
  {
    "text": "don't have to take a bunch of disparate parts off-the-shelf we connect out to your assets both your",
    "start": "2509570",
    "end": "2515750"
  },
  {
    "text": "IOT enabled assets as well as your ERP and CRM systems and pull all that data",
    "start": "2515750",
    "end": "2521240"
  },
  {
    "text": "into one place we use that in order to data Trent to transform the data to",
    "start": "2521240",
    "end": "2526670"
  },
  {
    "text": "process the data ultimately in service of getting it ready for data science so from the data science perspective we",
    "start": "2526670",
    "end": "2533060"
  },
  {
    "text": "allow engineers and data Sciences to build data science models to deploy data science models to train data science",
    "start": "2533060",
    "end": "2539750"
  },
  {
    "text": "models and then to operationally run them within our platform at scale while also measuring and tracking results of",
    "start": "2539750",
    "end": "2546200"
  },
  {
    "text": "those models and allowing our users to do that by bringing those results back into the platform which is something",
    "start": "2546200",
    "end": "2551900"
  },
  {
    "text": "that often goes on unnoticed at companies that are doing data where they're ultimately creating models",
    "start": "2551900",
    "end": "2558870"
  },
  {
    "text": "but they're not actually benchmarking and understanding how well they work so the last thing I'll say about our",
    "start": "2558870",
    "end": "2564660"
  },
  {
    "text": "platform is really this democracy democratization of data science and what that means is that we've really enabled",
    "start": "2564660",
    "end": "2570540"
  },
  {
    "text": "a platform that allows it to work across the spectrum of data science expertise and capability so you have junior data",
    "start": "2570540",
    "end": "2578610"
  },
  {
    "text": "scientists and data analysts that can come into the platform and with a few clicks deploy data science it's going to",
    "start": "2578610",
    "end": "2583980"
  },
  {
    "text": "create meaningful financial outcomes for your business but we also have expert level tools that allow data scientists",
    "start": "2583980",
    "end": "2590760"
  },
  {
    "text": "that are coding and working with our SDKs and toolkits to deploy models that run alongside uptake models within the",
    "start": "2590760",
    "end": "2597180"
  },
  {
    "text": "platform and get all the benefits of versioning and scalability and",
    "start": "2597180",
    "end": "2602430"
  },
  {
    "text": "operations and that performance management process that I was just talking about so wrapping up like I said",
    "start": "2602430",
    "end": "2611760"
  },
  {
    "text": "I was on my soapbox a little bit here about the way that we've approached these problems and the principles that",
    "start": "2611760",
    "end": "2617820"
  },
  {
    "text": "we think about and what that looks like but hopefully you can take some of these principles that I've had here and apply them to your business so firstly things",
    "start": "2617820",
    "end": "2626880"
  },
  {
    "text": "I want you to take away from this uptake is awesome I want you guys to come and talk to us more about it whether you",
    "start": "2626880",
    "end": "2633210"
  },
  {
    "text": "want are interested in our platform our applications curated datasets that we have we're at booth 27 14 over in the",
    "start": "2633210",
    "end": "2640170"
  },
  {
    "text": "Venetian so I'd love you guys to come over and talk to us more about what we're doing there second there's really",
    "start": "2640170",
    "end": "2646440"
  },
  {
    "text": "hard problems in this space an uptake is out here solving them and this is the approach that we've taken in order to solve them leveraging some of the",
    "start": "2646440",
    "end": "2654810"
  },
  {
    "text": "tenants that Dan and CJ talked about as well as some of the principles that I've been going through you have hard",
    "start": "2654810",
    "end": "2659970"
  },
  {
    "text": "problems and if you embody leaning into platform and thinking about data engineering in the right way you can",
    "start": "2659970",
    "end": "2665280"
  },
  {
    "text": "absolutely solve them to last you know AWS is it's there to make your lives",
    "start": "2665280",
    "end": "2673050"
  },
  {
    "text": "easier embrace it use it it really really does make your life easier so especially for",
    "start": "2673050",
    "end": "2678510"
  },
  {
    "text": "startups leverage as much as you can lean in to those managed services and make sure you're taking advantage of everything that they have to offer next once you're",
    "start": "2678510",
    "end": "2687619"
  },
  {
    "text": "up and running build learn repeat that process iterate and evolve we've talked a lot about the different ways to do",
    "start": "2687619",
    "end": "2693559"
  },
  {
    "text": "that and the life cycle that we've had to go through an uptake you're gonna have your own journey and it's not going to look like ours but make sure you're",
    "start": "2693559",
    "end": "2699289"
  },
  {
    "text": "building and Inter ating and learning from the different things that you're putting out there then finally make sure",
    "start": "2699289",
    "end": "2704630"
  },
  {
    "text": "that you and your teams are having fun we talked a lot about culture and the ways to affect it but you know that's really important too driving engineering",
    "start": "2704630",
    "end": "2711349"
  },
  {
    "text": "culture forward so I guess one more time",
    "start": "2711349",
    "end": "2717429"
  },
  {
    "text": "we have curated datasets we have a lot of use cases and case studies that we",
    "start": "2717429",
    "end": "2723410"
  },
  {
    "text": "can talk about at our booth 27:14 over in the Venetian please stop by and talk to us but now Dan CJ and I are all here",
    "start": "2723410",
    "end": "2730369"
  },
  {
    "text": "to answer questions if you guys have any I'm sure there are many questions first of all a round of applause that was a",
    "start": "2730369",
    "end": "2735559"
  },
  {
    "text": "great presentation so for those the way we're doing questions the best most",
    "start": "2735559",
    "end": "2741499"
  },
  {
    "text": "effective way if you go to slide o comm and push it in startup you can put in a question it appears here and we'll take",
    "start": "2741499",
    "end": "2747349"
  },
  {
    "text": "them off the stack this way so first one what it was the hardest problem you",
    "start": "2747349",
    "end": "2752689"
  },
  {
    "text": "solved an uptake yeah so I guess we've been talking about",
    "start": "2752689",
    "end": "2758970"
  },
  {
    "text": "this for quite a while it's really just all the variants in the system is Dan mentioned any change anywhere can affect",
    "start": "2758970",
    "end": "2766590"
  },
  {
    "text": "everything else downstream of the platform so really it's been how do we control that how do we control that at",
    "start": "2766590",
    "end": "2772140"
  },
  {
    "text": "scale not just for one tenant or for all of our tenants we've spent I think years trying to",
    "start": "2772140",
    "end": "2777870"
  },
  {
    "text": "tackle that problem first of all Philippe says sell it talk I think we",
    "start": "2777870",
    "end": "2784050"
  },
  {
    "text": "can all agree can you tell us how your platform handles a/b testing continuous model improvements yep I could probably",
    "start": "2784050",
    "end": "2790740"
  },
  {
    "text": "take that one as well so our data science engine that runs our model scoring allows us to deploy our",
    "start": "2790740",
    "end": "2798750"
  },
  {
    "text": "models for scoring in pilot mode so what we're able to do is deploy multiple versions of our model and then we have",
    "start": "2798750",
    "end": "2806220"
  },
  {
    "text": "something called our model performance report which gives that data-driven feedback that Brad was mentioning back",
    "start": "2806220",
    "end": "2811740"
  },
  {
    "text": "to the user to be able to deterministically say that yes this version is producing better insights of",
    "start": "2811740",
    "end": "2817050"
  },
  {
    "text": "this version and I have a quick question what is like what's a use case that came out of it that when you started you",
    "start": "2817050",
    "end": "2823590"
  },
  {
    "text": "didn't think this is gonna be something that was possible and you're kind of surprised at what you're able to accomplish with uptake or what you're able to detect sure I can take that one",
    "start": "2823590",
    "end": "2831720"
  },
  {
    "text": "so as I was saying there's we have a lot of use cases like this but I'll talk about one of the use cases within rail",
    "start": "2831720",
    "end": "2838650"
  },
  {
    "text": "we have a class-one railroad where we've been processing over 2 billion data points for them every single year that",
    "start": "2838650",
    "end": "2844860"
  },
  {
    "text": "feeds into over 34 different deployed prediction models that is",
    "start": "2844860",
    "end": "2850800"
  },
  {
    "text": "actually predicting failures for those locomotives we've predicted over 554",
    "start": "2850800",
    "end": "2857340"
  },
  {
    "text": "failures for those locomotives which translates over to 160,000 dollars per",
    "start": "2857340",
    "end": "2862470"
  },
  {
    "text": "locomotive per year which is you know millions of dollars in savings for those",
    "start": "2862470",
    "end": "2868110"
  },
  {
    "text": "at the same time it's allowed the technicians on site to have 2,000 days",
    "start": "2868110",
    "end": "2875090"
  },
  {
    "text": "prior warning to when those failures are going to occur which just allows them to kind of shop assets which is a very",
    "start": "2875090",
    "end": "2881880"
  },
  {
    "text": "expensive thing to do at the right time in order to be able to solve problems before they happen out on the",
    "start": "2881880",
    "end": "2887920"
  },
  {
    "text": "and just to add on they're like that's the startup way proof of concept we get",
    "start": "2887920",
    "end": "2893230"
  },
  {
    "text": "a huge packet of data what can we do with it you know and don't limit yourself this next person is a very",
    "start": "2893230",
    "end": "2901000"
  },
  {
    "text": "protective over their identity so naturally their question is how do you handle access control for the data so I",
    "start": "2901000",
    "end": "2908380"
  },
  {
    "text": "can jump into that one we take data entitlement very seriously same for a multi-tenant support so when you're on",
    "start": "2908380",
    "end": "2915190"
  },
  {
    "text": "the platform you feel like the platform's all yours and indeed your data is secured all the way down to like",
    "start": "2915190",
    "end": "2922000"
  },
  {
    "text": "the row level storage we're able to look at auditing information we also have a",
    "start": "2922000",
    "end": "2927990"
  },
  {
    "text": "into end authorization framework that sits in front of everything so every micro service has access to that so we",
    "start": "2927990",
    "end": "2935200"
  },
  {
    "text": "get context about who you are what your policies are what data you have access to and that that flows through to even",
    "start": "2935200",
    "end": "2940839"
  },
  {
    "text": "the back-end services so things that are running like model performance reporting or doing pipelining they're all entitled",
    "start": "2940839",
    "end": "2948309"
  },
  {
    "text": "and masters control is all in place for those I think that's a common challenge you know data is dirty so how do you",
    "start": "2948309",
    "end": "2955779"
  },
  {
    "text": "handle that yeah you talk a little bit how you clean that up how you work with that yeah so I can take that one so",
    "start": "2955779",
    "end": "2963460"
  },
  {
    "text": "that's a common challenge with any data integration I've been dealing with this years before I even came to uptake and",
    "start": "2963460",
    "end": "2969309"
  },
  {
    "text": "really the sort of force multiplier that we found here is sort of moving away",
    "start": "2969309",
    "end": "2974980"
  },
  {
    "text": "from every time we have a new data set or a new data source not requiring an",
    "start": "2974980",
    "end": "2980109"
  },
  {
    "text": "engineering team to spend weeks or months configuring some system and we've tried out a number of different",
    "start": "2980109",
    "end": "2985150"
  },
  {
    "text": "approaches there and really transitioning to that self-service model where you don't necessarily need to know",
    "start": "2985150",
    "end": "2991420"
  },
  {
    "text": "all of the engineering underpinnings of the platform you just need to be able to work with the data in a simple mechanism",
    "start": "2991420",
    "end": "2997869"
  },
  {
    "text": "to get it in and then we have some drag-and-drop you is that at least for the simple use cases make it very",
    "start": "2997869",
    "end": "3003480"
  },
  {
    "text": "trivial to say I want data from data source a I want to filter out these",
    "start": "3003480",
    "end": "3008609"
  },
  {
    "text": "things transform them and the pipes up to these data stores and make",
    "start": "3008609",
    "end": "3013870"
  },
  {
    "text": "that sort of end end workflow down to the level of minutes where it used to",
    "start": "3013870",
    "end": "3018880"
  },
  {
    "text": "took it used to take us weeks or even longer next question a lot of people wonder",
    "start": "3018880",
    "end": "3024670"
  },
  {
    "text": "this I mean we have over close to a thousand plus services 130-plus how do",
    "start": "3024670",
    "end": "3030220"
  },
  {
    "text": "you kind of how do you gauge what to use how do you test stuff how do you figure out what the right services are even",
    "start": "3030220",
    "end": "3037120"
  },
  {
    "text": "discovering them to solve the problems you're tackling you talk about kind of how'd you discover these and test these out so I can kind of jump in there I",
    "start": "3037120",
    "end": "3044560"
  },
  {
    "text": "guess the first thing that kind of comes back to is what problem are you solving and how are you kind of tackling that so",
    "start": "3044560",
    "end": "3050650"
  },
  {
    "text": "getting clear about that laser focus on what you're gonna tackle and then looking for all the supporting pieces",
    "start": "3050650",
    "end": "3056170"
  },
  {
    "text": "for it and diving into what can AWS help me with there I think you know the other thing if you notice in Brad's slide",
    "start": "3056170",
    "end": "3062860"
  },
  {
    "text": "where we talked about you know we started off as a monolith and we moved to micro services now our platform",
    "start": "3062860",
    "end": "3067920"
  },
  {
    "text": "understand that there's an evolution and it's totally okay to get your proof of concept up and running so like build it",
    "start": "3067920",
    "end": "3074980"
  },
  {
    "text": "build it right and then build it fast don't try to do all those things at once I'd also say any of the AWS like",
    "start": "3074980",
    "end": "3081940"
  },
  {
    "text": "architecture or solution experts they can totally like you just explain the problem they'll jump in and play in the",
    "start": "3081940",
    "end": "3087880"
  },
  {
    "text": "right direction I think something I always try to encourage people to do is you know you might know how to solve",
    "start": "3087880",
    "end": "3093220"
  },
  {
    "text": "something two years ago but there's always new stuff coming out so before you start building something just search just Google there's somebody who was",
    "start": "3093220",
    "end": "3099940"
  },
  {
    "text": "searching who was doing machine learning two sessions ago and they looked at stage maker just came out that day and",
    "start": "3099940",
    "end": "3105940"
  },
  {
    "text": "like oh this is perfect I'm gonna use this now so there's always some newer easier faster way to do something",
    "start": "3105940",
    "end": "3111040"
  },
  {
    "text": "I'm just stayed you cated on it have you thought about deploying your software on Fram or is it always on your systems you",
    "start": "3111040",
    "end": "3118150"
  },
  {
    "text": "talk about that is that a limitation for your customers yes we've thought about this quite a bit",
    "start": "3118150",
    "end": "3126730"
  },
  {
    "text": "we ultimately can kind of go across different clouds so we can meet you where you're at there's definitely a",
    "start": "3126730",
    "end": "3133540"
  },
  {
    "text": "significant population of enterprise clients that especially within the industrial space are having trouble in",
    "start": "3133540",
    "end": "3139660"
  },
  {
    "text": "their early part of their digital transformation journey going from on-prem into the cloud in the first place so helping them evangelize the",
    "start": "3139660",
    "end": "3147160"
  },
  {
    "text": "value of doing that both from a security perspective and a lot of other things is one of the things that we have to do",
    "start": "3147160",
    "end": "3152589"
  },
  {
    "text": "quite often but we have actually deployed into customers on-premise systems and integrated with them so",
    "start": "3152589",
    "end": "3159339"
  },
  {
    "text": "we've done that in the past and that definitely creates when we talk about platform and thinking about that that",
    "start": "3159339",
    "end": "3166270"
  },
  {
    "text": "definitely creates some compromises and some trade-offs that we have to make when we're thinking about doing that so we only do that in places where it's",
    "start": "3166270",
    "end": "3173440"
  },
  {
    "text": "really critical for us to do that and frankly the size of the deal that we have is really really large in general",
    "start": "3173440",
    "end": "3180460"
  },
  {
    "text": "we're being cloud agnostic so that we can work in AWS and we can work in other cloud providers so that we can meet you",
    "start": "3180460",
    "end": "3186369"
  },
  {
    "text": "where you're at and then there's you know a decent number of clients to just say hey look we're just starting our digital transformation journey so you",
    "start": "3186369",
    "end": "3193329"
  },
  {
    "text": "can take our data and you can put it wherever you want and so our kind of home base for where we go naturally is",
    "start": "3193329",
    "end": "3198609"
  },
  {
    "text": "just to put it up in Amazon fantastic super condensed amount of information really appreciate it",
    "start": "3198609",
    "end": "3204579"
  },
  {
    "text": "yeah I'm giving a round of applause for a great talk thank you guys",
    "start": "3204579",
    "end": "3210450"
  }
]